[{"meta_id":"20825","post_id":"3811","meta_key":"_edit_lock","meta_value":"1615941927:20"},{"meta_id":"20826","post_id":"3811","meta_key":"_edit_last","meta_value":"20"},{"meta_id":"20827","post_id":"3811","meta_key":"categorizar","meta_value":"a:5:{i:0;s:2:\"50\";i:1;s:2:\"47\";i:2;s:2:\"76\";i:3;s:2:\"37\";i:4;s:2:\"33\";}"},{"meta_id":"20828","post_id":"3811","meta_key":"_categorizar","meta_value":"field_602d8e8b988e5"},{"meta_id":"20831","post_id":"3811","meta_key":"_elementor_edit_mode","meta_value":"builder"},{"meta_id":"20832","post_id":"3811","meta_key":"_elementor_template_type","meta_value":"wp-page"},{"meta_id":"20833","post_id":"3811","meta_key":"_elementor_version","meta_value":"3.1.1"},{"meta_id":"20834","post_id":"3811","meta_key":"_elementor_pro_version","meta_value":"3.1.0"},{"meta_id":"20906","post_id":"3811","meta_key":"_elementor_data","meta_value":[{"id":"39576312","elType":"section","settings":{"content_width":{"unit":"px","size":"840"},"gap":"extended","content_position":"middle","padding":{"unit":"px","top":"100","right":"0","bottom":"100","left":"0","isLinked":""},"background_background":"classic","background_overlay_background":"classic","background_overlay_color":"#473427","background_overlay_opacity":{"unit":"px","size":"0.75"},"background_position":"center center","background_size":"cover","shape_divider_bottom":"tilt","shape_divider_bottom_height":{"unit":"px","size":"40"},"shape_divider_bottom_flip":"yes","background_color":"#473b31","background_overlay_image":{"id":"3814","url":"https:\/\/ponceleon.site\/demos\/wp-content\/uploads\/sites\/84\/2021\/03\/fancycrave-254180-unsplash.jpg"},"background_overlay_size":"cover","overlay_blend_mode":"multiply"},"elements":[{"id":"47c752eb","elType":"column","settings":{"_column_size":"100","margin":{"unit":"px","top":"60","right":"0","bottom":"60","left":"0","isLinked":""},"padding":{"unit":"%","top":"","right":"","bottom":"","left":"","isLinked":""},"margin_mobile":{"unit":"px","top":"0","right":"0","bottom":"0","left":"0","isLinked":""}},"elements":[{"id":"5e464efb","elType":"section","settings":{"gap":"no","content_position":"middle","structure":"30","animation":"fadeIn","animation_duration":"slow","animation_delay":"600"},"elements":[{"id":"708c561d","elType":"column","settings":{"_column_size":"33","_inline_size":"44.691"},"elements":[{"id":"77e700b7","elType":"widget","settings":{"editor":"<p>Est. 2000 east avenue 192<\/p>","align":"right","text_color":"#c1c1c1","typography_typography":"custom","typography_font_family":"Poppins","typography_font_size":{"unit":"rem","size":"0.8"},"typography_font_weight":"400","typography_text_transform":"uppercase","align_mobile":"center","typography_letter_spacing":{"unit":"px","size":"2.6"}},"elements":[],"widgetType":"text-editor"}],"isInner":"1"},{"id":"2511f386","elType":"column","settings":{"_column_size":"33","_inline_size":"10.247"},"elements":[{"id":"60d929a3","elType":"widget","settings":{"image":{"id":"3815","url":"https:\/\/ponceleon.site\/demos\/wp-content\/uploads\/sites\/84\/2021\/03\/button-white-illustrio.png"},"width":{"unit":"%","size":"70"}},"elements":[],"widgetType":"image"}],"isInner":"1"},{"id":"541d6720","elType":"column","settings":{"_column_size":"33","_inline_size":"45.055"},"elements":[{"id":"1cb8bf4d","elType":"widget","settings":{"editor":"<p>perfection in quality<\/p>","align":"left","text_color":"#c1c1c1","typography_typography":"custom","typography_font_family":"Poppins","typography_font_size":{"unit":"rem","size":"0.8"},"typography_font_weight":"400","typography_text_transform":"uppercase","align_mobile":"center","typography_letter_spacing":{"unit":"px","size":"2.6"}},"elements":[],"widgetType":"text-editor"}],"isInner":"1"}],"isInner":"1"},{"id":"4524ffbc","elType":"widget","settings":{"headline_style":"rotate","animation_type":"wave","before_text":"Welcome to city's","highlighted_text":"","rotating_text":"Best Store\nTop Shop","tag":"h1","title_color":"#ffffff","title_typography_typography":"custom","title_typography_font_family":"Playfair Display","title_typography_font_size":{"unit":"px","size":"84"},"title_typography_font_size_tablet":{"unit":"px","size":"70"},"title_typography_font_size_mobile":{"unit":"px","size":"42"},"title_typography_font_weight":"800","title_typography_text_transform":"capitalize","title_typography_letter_spacing":{"unit":"px","size":"-2.3"},"words_color":"#ffffff","words_typography_typography":"custom","words_typography_font_family":"Playfair Display","words_typography_font_weight":"800","words_typography_text_transform":"none","_margin":{"unit":"px","top":"-60","right":"0","bottom":"-40","left":"0","isLinked":""},"_animation":"fadeIn","animation_duration":"slow","_margin_mobile":{"unit":"px","top":"0","right":"0","bottom":"0","left":"0","isLinked":"1"}},"elements":[],"widgetType":"animated-headline"},{"id":"15be97f3","elType":"widget","settings":{"weight":{"unit":"px","size":"60"},"color":"rgba(255,255,255,0.31)","width":{"unit":"px","size":"1"},"align":"center","_animation":"fadeIn","animation_duration":"slow","_animation_delay":"1200","text":"Separador"},"elements":[],"widgetType":"divider"},{"id":"98cb455","elType":"widget","settings":{"editor":"<p>Lorem ipsum dolor sit amet, consectetur adipiscing elit. Duis mollis metus in urna maximus maximus. Nam faucibus elit ut nunc consequat, sit amet auctor orci aliquet. Proin commodo diam quis est rhoncus pulvinar. Cras mattis ultricies lectus, vel scelerisque urna fermentum sed. Maecenas id sodales augue. Morbi eget mauris erat.<\/p>","align":"center","text_color":"rgba(255,255,255,0.81)","typography_typography":"custom","typography_font_family":"PT Serif","typography_font_size":{"unit":"px","size":"15"},"typography_line_height":{"unit":"em","size":"1.7"},"_margin":{"unit":"px","top":"0","right":"0","bottom":"60","left":"0","isLinked":""},"_animation":"fadeInUp","_animation_delay":"300","hide_mobile":"hidden-phone"},"elements":[],"widgetType":"text-editor"},{"id":"38f54bec","elType":"section","settings":{"gap":"extended","structure":"20"},"elements":[{"id":"5a4b6aed","elType":"column","settings":{"_column_size":"50"},"elements":[{"id":"efccc57","elType":"widget","settings":{"text":"View Detail","align":"right","size":"lg","typography_typography":"custom","typography_font_family":"Poppins","typography_font_size":{"unit":"px","size":"12"},"typography_font_weight":"500","typography_text_transform":"uppercase","typography_letter_spacing":{"unit":"px","size":"1"},"button_text_color":"#ffffff","background_color":"#cea75a","hover_color":"#cea75a","button_background_hover_color":"#ffffff","border_radius":{"unit":"px","top":"0","right":"0","bottom":"0","left":"0","isLinked":"1"},"_animation":"fadeInUp","_animation_delay":"600","button_hover_border_color":"#ffffff","border_border":"solid","border_width":{"unit":"px","top":"2","right":"2","bottom":"2","left":"2","isLinked":"1"},"border_color":"#cea75a","align_mobile":"center"},"elements":[],"widgetType":"button"}],"isInner":"1"},{"id":"3f99e59c","elType":"column","settings":{"_column_size":"50"},"elements":[{"id":"6f03b36a","elType":"widget","settings":{"text":"Contact us","align":"left","size":"lg","typography_typography":"custom","typography_font_family":"Poppins","typography_font_size":{"unit":"px","size":"12"},"typography_font_weight":"500","typography_text_transform":"uppercase","typography_letter_spacing":{"unit":"px","size":"1"},"button_text_color":"#ffffff","background_color":"rgba(206,167,90,0)","hover_color":"#ffffff","button_background_hover_color":"#cea75a","border_radius":{"unit":"px","top":"0","right":"0","bottom":"0","left":"0","isLinked":"1"},"_animation":"fadeInUp","_animation_delay":"800","button_hover_border_color":"#cea75a","border_border":"dashed","border_width":{"unit":"px","top":"2","right":"2","bottom":"2","left":"2","isLinked":"1"},"align_mobile":"center"},"elements":[],"widgetType":"button"}],"isInner":"1"}],"isInner":"1"}],"isInner":""}],"isInner":""},{"id":"1c9797a7","elType":"section","settings":{"gap":"no","background_background":"classic","background_color":"#ffffff","padding":{"unit":"px","top":"60","right":"0","bottom":"60","left":"0","isLinked":""}},"elements":[{"id":"1d4fe523","elType":"column","settings":{"_column_size":"100"},"elements":[{"id":"7e49c069","elType":"section","settings":{"content_width":{"unit":"px","size":"840"},"gap":"extended"},"elements":[{"id":"39757c83","elType":"column","settings":{"_column_size":"100"},"elements":[{"id":"39e5165c","elType":"widget","settings":{"title":"About us","align":"center","title_color":"#020202","typography_typography":"custom","typography_font_family":"Playfair Display","typography_font_size":{"unit":"px","size":"48"},"typography_font_weight":"800","typography_text_transform":"capitalize","typography_letter_spacing":{"unit":"px","size":"-2.3"},"_margin":{"unit":"px","top":"40","right":"0","bottom":"0","left":"0","isLinked":""},"typography_font_size_tablet":{"unit":"em","size":""},"typography_font_size_mobile":{"unit":"px","size":"42"},"_animation":"fadeIn","animation_duration":"slow"},"elements":[],"widgetType":"heading"},{"id":"55b513f5","elType":"widget","settings":{"editor":"<p>Quisque semper dui non bibendum iaculis. Quisque quis finibus neque. Cras nunc diam, pharetra et nisl a, semper bibendum elit. Nunc fringilla massa luctus, rutrum lorem cursus, luctus libero. <\/p>","align":"center","text_color":"#8e8e8e","typography_typography":"custom","typography_font_family":"PT Serif","typography_font_size":{"unit":"px","size":"15"},"typography_line_height":{"unit":"em","size":"1.7"},"_margin":{"unit":"px","top":"0","right":"0","bottom":"0","left":"0","isLinked":""},"typography_font_style":"italic","_padding":{"unit":"%","top":"","right":"","bottom":"","left":"","isLinked":"1"},"_animation":"fadeInUp","_animation_delay":"300"},"elements":[],"widgetType":"text-editor"},{"id":"9b9643","elType":"widget","settings":{"weight":{"unit":"px","size":"60"},"color":"rgba(2,2,2,0.31)","width":{"unit":"px","size":"1"},"align":"center","_animation":"fadeIn","animation_duration":"slow","_animation_delay":"1200","text":"Separador"},"elements":[],"widgetType":"divider"}],"isInner":"1"}],"isInner":"1"},{"id":"25215f7f","elType":"section","settings":{"padding_tablet":{"unit":"em","top":"2","right":"2","bottom":"2","left":"2","isLinked":"1"}},"elements":[{"id":"1407e57d","elType":"column","settings":{"_column_size":"100"},"elements":[{"id":"595645bd","elType":"widget","settings":{"slides":[{"heading":"Premium Quality","description":"Lorem ipsum dolor sit amet consectetur adipiscing elit dolor","button_text":"","background_color":"rgba(26,188,156,0)","_id":"7ebc077","background_image":{"id":"3816","url":"https:\/\/ponceleon.site\/demos\/wp-content\/uploads\/sites\/84\/2021\/03\/artificial-photography-119298-unsplash.jpg"},"background_ken_burns":"yes","background_overlay":"yes","background_overlay_color":"rgba(71,59,49,0.51)","repeater_text_shadow_text_shadow":{"horizontal":"0","vertical":"0","blur":"10","color":"rgba(0,0,0,0.3)"}},{"heading":"Fast Process","description":"Lorem ipsum dolor sit amet consectetur adipiscing elit dolor","button_text":"","background_color":"rgba(26,188,156,0)","_id":"b773270","background_image":{"id":"3817","url":"https:\/\/ponceleon.site\/demos\/wp-content\/uploads\/sites\/84\/2021\/03\/lauren-fleischmann-469994-unsplash.jpg"},"background_ken_burns":"yes","background_overlay":"yes","background_overlay_color":"rgba(71,59,49,0.51)","repeater_text_shadow_text_shadow":{"horizontal":"0","vertical":"0","blur":"10","color":"rgba(0,0,0,0.3)"}}],"slides_height":{"unit":"px","size":"625"},"slides_height_tablet":{"unit":"px","size":"425"},"slides_height_mobile":{"unit":"px","size":"420"},"navigation":"dots","pause_on_hover":"","content_animation":"fadeInDown","content_max_width":{"unit":"px","size":"445"},"heading_spacing":{"unit":"px","size":"0"},"heading_color":"#ffffff","heading_typography_typography":"custom","heading_typography_font_family":"Poppins","heading_typography_font_size":{"unit":"px","size":"37"},"heading_typography_font_weight":"600","heading_typography_text_transform":"uppercase","description_spacing":{"unit":"px","size":"0"},"description_color":"#cea75a","description_typography_typography":"custom","description_typography_font_family":"Playfair Display","description_typography_font_size":{"unit":"px","size":"21"},"description_typography_font_style":"italic","description_typography_line_height":{"unit":"em","size":"1"},"dots_color":"#ffffff"},"elements":[],"widgetType":"slides"},{"id":"1c78e9a2","elType":"widget","settings":{"editor":"<p>Nunc molestie gravida vulputate vivamus a purus at mi sollicitudin convallis morbi at vehicula felis sed aliquam dapibus enim at porttitor libero lobortis maximus.<\/p>","text_color":"#565656","typography_typography":"custom","typography_font_family":"PT Serif","typography_font_size":{"unit":"px","size":"20"},"typography_line_height":{"unit":"em","size":"1.7"},"_margin":{"unit":"%","top":"","right":"","bottom":"","left":"","isLinked":""},"_padding":{"unit":"%","top":"","right":"","bottom":"","left":"","isLinked":"1"},"_animation_delay":"300","typography_font_style":"italic","_border_border":"double","_border_width":{"unit":"px","top":"4","right":"0","bottom":"4","left":"0","isLinked":""},"align":"center"},"elements":[],"widgetType":"text-editor"}],"isInner":"1"}],"isInner":"1"},{"id":"76a8eaf6","elType":"section","settings":{"gap":"extended","structure":"20","padding_tablet":{"unit":"em","top":"2","right":"2","bottom":"2","left":"2","isLinked":"1"}},"elements":[{"id":"76277986","elType":"column","settings":{"_column_size":"50","_inline_size_tablet":"50"},"elements":[{"id":"4664fd23","elType":"widget","settings":{"editor":"<p>Suspendisse in justo quam. Integer at porttitor libero. Interdum et malesuada fames ac ante ipsum primis in faucibus. Nam fermentum varius tempor.<\/p><p>Vivamus a purus at mi sollicitudin convallis. Morbi at vehicula felis. Donec id nisi dui. Ut quam nunc, lobortis id tempus vel, fringilla et arcu.Curabitur viverra sit amet nisl nec accumsan. Nam placerat aliquet, vel feugiat est mollis. Donec consequat, odio id tristique mattis, ipsum metus varius nisi, non ultricies erat ipsum vel dui.<\/p>","text_color":"#8e8e8e","typography_typography":"custom","typography_font_family":"PT Serif","typography_font_size":{"unit":"px","size":"14"},"typography_line_height":{"unit":"em","size":"1.7"},"_margin":{"unit":"px","top":"0","right":"0","bottom":"0","left":"0","isLinked":""},"_padding":{"unit":"%","top":"","right":"","bottom":"","left":"","isLinked":"1"},"_animation_delay":"300"},"elements":[],"widgetType":"text-editor"}],"isInner":"1"},{"id":"5fb38535","elType":"column","settings":{"_column_size":"50","_inline_size_tablet":"50"},"elements":[{"id":"6588447a","elType":"widget","settings":{"editor":"<p>Suspendisse in justo quam. Integer at porttitor libero. Interdum et malesuada fames ac ante ipsum primis in faucibus. Nam fermentum varius tempor.<\/p><p>Curabitur viverra sit amet nisl nec accumsan. Nam placerat purus non ex aliquet, vel feugiat est mollis. Donec consequat, odio id tristique mattis, ipsum metus varius nisi, non ultricies erat ipsum vel dui.<\/p>","text_color":"#8e8e8e","typography_typography":"custom","typography_font_family":"PT Serif","typography_font_size":{"unit":"px","size":"14"},"typography_line_height":{"unit":"em","size":"1.7"},"_margin":{"unit":"px","top":"0","right":"0","bottom":"0","left":"0","isLinked":""},"_padding":{"unit":"%","top":"","right":"","bottom":"","left":"","isLinked":"1"},"_animation_delay":"300"},"elements":[],"widgetType":"text-editor"}],"isInner":"1"}],"isInner":"1"},{"id":"77f42f9c","elType":"section","settings":{"content_width":{"unit":"px","size":"840"},"gap":"extended"},"elements":[{"id":"2d78770a","elType":"column","settings":{"_column_size":"100"},"elements":[{"id":"1613b4cb","elType":"widget","settings":{"text":"More about us","align":"center","size":"lg","typography_typography":"custom","typography_font_family":"Poppins","typography_font_size":{"unit":"px","size":"12"},"typography_font_weight":"600","typography_text_transform":"uppercase","typography_letter_spacing":{"unit":"px","size":"1"},"button_text_color":"#cea75a","background_color":"rgba(206,167,90,0)","hover_color":"#000000","button_background_hover_color":"rgba(229,229,229,0)","border_radius":{"unit":"px","top":"0","right":"0","bottom":"0","left":"0","isLinked":"1"},"_margin":{"unit":"px","top":"0","right":"0","bottom":"0","left":"0","isLinked":""},"_animation_delay":"600","typography_text_decoration":"underline"},"elements":[],"widgetType":"button"}],"isInner":"1"}],"isInner":"1"}],"isInner":""}],"isInner":""},{"id":"77e53b3","elType":"section","settings":{"gap":"no","background_background":"classic","background_color":"#f9f9f9","padding":{"unit":"px","top":"60","right":"0","bottom":"60","left":"0","isLinked":""},"border_border":"dotted","border_width":{"unit":"px","top":"3","right":"0","bottom":"0","left":"0","isLinked":""},"border_color":"rgba(0,0,0,0.26)","shape_divider_top_height":{"unit":"px","size":"84"},"shape_divider_top_negative":"yes","margin":{"unit":"px","top":"45","right":"0","bottom":"0","left":"0","isLinked":""}},"elements":[{"id":"79b3385","elType":"column","settings":{"_column_size":"100"},"elements":[{"id":"56615fa8","elType":"widget","settings":{"image":{"id":"3818","url":"https:\/\/ponceleon.site\/demos\/wp-content\/uploads\/sites\/84\/2021\/03\/scissors-clip.png"},"image_size":"full","align":"left","width":{"unit":"%","size":"12"},"opacity":{"unit":"px","size":"0.3"},"_margin":{"unit":"px","top":"-95","right":"0","bottom":"0","left":"0","isLinked":""},"_padding":{"unit":"px","top":"0","right":"0","bottom":"0","left":"0","isLinked":""},"_z_index":"11","align_tablet":"center","width_tablet":{"unit":"%","size":"18"}},"elements":[],"widgetType":"image"},{"id":"6fabbbfb","elType":"section","settings":{"content_width":{"unit":"px","size":"840"},"gap":"extended"},"elements":[{"id":"14b2422d","elType":"column","settings":{"_column_size":"100"},"elements":[{"id":"463781e8","elType":"widget","settings":{"title":"What We do","align":"center","title_color":"#020202","typography_typography":"custom","typography_font_family":"Playfair Display","typography_font_size":{"unit":"px","size":"48"},"typography_font_weight":"800","typography_text_transform":"capitalize","typography_letter_spacing":{"unit":"px","size":"-2.3"},"_margin":{"unit":"px","top":"40","right":"0","bottom":"0","left":"0","isLinked":""},"typography_font_size_tablet":{"unit":"em","size":""},"typography_font_size_mobile":{"unit":"px","size":"42"},"_animation":"fadeIn","animation_duration":"slow"},"elements":[],"widgetType":"heading"},{"id":"2d44c97f","elType":"widget","settings":{"editor":"<p>Quisque semper dui non bibendum iaculis. Quisque quis finibus neque. Cras nunc diam, pharetra et nisl a, semper bibendum elit. Nunc fringilla massa luctus, rutrum lorem cursus, luctus libero. <\/p>","align":"center","text_color":"#8e8e8e","typography_typography":"custom","typography_font_family":"PT Serif","typography_font_size":{"unit":"px","size":"15"},"typography_line_height":{"unit":"em","size":"1.7"},"_margin":{"unit":"px","top":"0","right":"0","bottom":"0","left":"0","isLinked":""},"typography_font_style":"italic","_padding":{"unit":"%","top":"","right":"","bottom":"","left":"","isLinked":"1"},"_animation":"fadeInUp","_animation_delay":"300"},"elements":[],"widgetType":"text-editor"},{"id":"88125ed","elType":"widget","settings":{"weight":{"unit":"px","size":"60"},"color":"#635a45","width":{"unit":"px","size":"1"},"align":"center","_animation":"fadeIn","animation_duration":"slow","_animation_delay":"1200","text":"Separador"},"elements":[],"widgetType":"divider"}],"isInner":"1"}],"isInner":"1"},{"id":"418596bd","elType":"section","settings":{"gap":"extended","structure":"30"},"elements":[{"id":"7a89a541","elType":"column","settings":{"_column_size":"33","_inline_size_tablet":"33","padding":{"unit":"em","top":"2","right":"2","bottom":"2","left":"2","isLinked":"1"},"padding_tablet":{"unit":"em","top":"1","right":"1","bottom":"1","left":"1","isLinked":"1"}},"elements":[{"id":"74ff9191","elType":"widget","settings":{"image":{"id":"3819","url":"https:\/\/ponceleon.site\/demos\/wp-content\/uploads\/sites\/84\/2021\/03\/tailor-blk-illustrio.png"},"title_text":"This is the heading","description_text":"Click edit button to change this text. Lorem ipsum dolor sit amet, consectetur adipiscing elit. Ut elit tellus, luctus nec ullamcorper mattis, pulvinar dapibus leo.","image_size":{"unit":"%","size":"17"},"content_vertical_alignment":"middle","title_bottom_space":{"unit":"px","size":"20"},"title_color":"#020202","title_typography_typography":"custom","title_typography_font_family":"Poppins","title_typography_font_size":{"unit":"px","size":"15"},"title_typography_font_weight":"700","title_typography_text_transform":"uppercase","description_typography_typography":"custom","description_typography_font_family":"PT Serif","description_typography_font_size":{"unit":"px","size":"14"},"description_typography_line_height":{"unit":"em","size":"1.7"}},"elements":[],"widgetType":"image-box"}],"isInner":"1"},{"id":"48a724f8","elType":"column","settings":{"_column_size":"33","_inline_size_tablet":"33","padding":{"unit":"em","top":"2","right":"2","bottom":"2","left":"2","isLinked":"1"},"padding_tablet":{"unit":"em","top":"1","right":"1","bottom":"1","left":"1","isLinked":"1"}},"elements":[{"id":"51eaaccd","elType":"widget","settings":{"image":{"id":"3820","url":"https:\/\/ponceleon.site\/demos\/wp-content\/uploads\/sites\/84\/2021\/03\/needle-blk-illustrio.png"},"title_text":"This is the heading","description_text":"Click edit button to change this text. Lorem ipsum dolor sit amet, consectetur adipiscing elit. Ut elit tellus, luctus nec ullamcorper mattis, pulvinar dapibus leo.","image_size":{"unit":"%","size":"17"},"content_vertical_alignment":"middle","title_bottom_space":{"unit":"px","size":"20"},"title_color":"#020202","title_typography_typography":"custom","title_typography_font_family":"Poppins","title_typography_font_size":{"unit":"px","size":"15"},"title_typography_font_weight":"700","title_typography_text_transform":"uppercase","description_typography_typography":"custom","description_typography_font_family":"PT Serif","description_typography_font_size":{"unit":"px","size":"14"},"description_typography_line_height":{"unit":"em","size":"1.7"}},"elements":[],"widgetType":"image-box"}],"isInner":"1"},{"id":"24a1c2af","elType":"column","settings":{"_column_size":"33","_inline_size_tablet":"33","padding":{"unit":"em","top":"2","right":"2","bottom":"2","left":"2","isLinked":"1"},"padding_tablet":{"unit":"em","top":"1","right":"1","bottom":"1","left":"1","isLinked":"1"}},"elements":[{"id":"4ace07b7","elType":"widget","settings":{"image":{"id":"3821","url":"https:\/\/ponceleon.site\/demos\/wp-content\/uploads\/sites\/84\/2021\/03\/button-black-illustrio.png"},"title_text":"This is the heading","description_text":"Click edit button to change this text. Lorem ipsum dolor sit amet, consectetur adipiscing elit. Ut elit tellus, luctus nec ullamcorper mattis, pulvinar dapibus leo.","image_size":{"unit":"%","size":"17"},"content_vertical_alignment":"middle","title_bottom_space":{"unit":"px","size":"20"},"title_color":"#020202","title_typography_typography":"custom","title_typography_font_family":"Poppins","title_typography_font_size":{"unit":"px","size":"15"},"title_typography_font_weight":"700","title_typography_text_transform":"uppercase","description_typography_typography":"custom","description_typography_font_family":"PT Serif","description_typography_font_size":{"unit":"px","size":"14"},"description_typography_line_height":{"unit":"em","size":"1.7"}},"elements":[],"widgetType":"image-box"}],"isInner":"1"}],"isInner":"1"},{"id":"30b2d2f0","elType":"section","settings":{"gap":"extended","structure":"30"},"elements":[{"id":"6dbdcca2","elType":"column","settings":{"_column_size":"33","_inline_size_tablet":"33","padding":{"unit":"em","top":"2","right":"2","bottom":"2","left":"2","isLinked":"1"},"padding_tablet":{"unit":"em","top":"1","right":"1","bottom":"1","left":"1","isLinked":"1"}},"elements":[{"id":"4ce99942","elType":"widget","settings":{"image":{"id":"3822","url":"https:\/\/ponceleon.site\/demos\/wp-content\/uploads\/sites\/84\/2021\/03\/thimble-blk-illustrio.png"},"title_text":"This is the heading","description_text":"Click edit button to change this text. Lorem ipsum dolor sit amet, consectetur adipiscing elit. Ut elit tellus, luctus nec ullamcorper mattis, pulvinar dapibus leo.","image_size":{"unit":"%","size":"17"},"content_vertical_alignment":"middle","title_bottom_space":{"unit":"px","size":"20"},"title_color":"#020202","title_typography_typography":"custom","title_typography_font_family":"Poppins","title_typography_font_size":{"unit":"px","size":"15"},"title_typography_font_weight":"700","title_typography_text_transform":"uppercase","description_typography_typography":"custom","description_typography_font_family":"PT Serif","description_typography_font_size":{"unit":"px","size":"14"},"description_typography_line_height":{"unit":"em","size":"1.7"}},"elements":[],"widgetType":"image-box"}],"isInner":"1"},{"id":"399c3141","elType":"column","settings":{"_column_size":"33","_inline_size_tablet":"33","padding":{"unit":"em","top":"2","right":"2","bottom":"2","left":"2","isLinked":"1"},"padding_tablet":{"unit":"em","top":"1","right":"1","bottom":"1","left":"1","isLinked":"1"}},"elements":[{"id":"434138b5","elType":"widget","settings":{"image":{"id":"3823","url":"https:\/\/ponceleon.site\/demos\/wp-content\/uploads\/sites\/84\/2021\/03\/zipper-blk-illustrio.png"},"title_text":"This is the heading","description_text":"Click edit button to change this text. Lorem ipsum dolor sit amet, consectetur adipiscing elit. Ut elit tellus, luctus nec ullamcorper mattis, pulvinar dapibus leo.","image_size":{"unit":"%","size":"17"},"content_vertical_alignment":"middle","title_bottom_space":{"unit":"px","size":"20"},"title_color":"#020202","title_typography_typography":"custom","title_typography_font_family":"Poppins","title_typography_font_size":{"unit":"px","size":"15"},"title_typography_font_weight":"700","title_typography_text_transform":"uppercase","description_typography_typography":"custom","description_typography_font_family":"PT Serif","description_typography_font_size":{"unit":"px","size":"14"},"description_typography_line_height":{"unit":"em","size":"1.7"}},"elements":[],"widgetType":"image-box"}],"isInner":"1"},{"id":"186e58cb","elType":"column","settings":{"_column_size":"33","_inline_size_tablet":"33","padding":{"unit":"em","top":"2","right":"2","bottom":"2","left":"2","isLinked":"1"},"padding_tablet":{"unit":"em","top":"1","right":"1","bottom":"1","left":"1","isLinked":"1"}},"elements":[{"id":"7f2e50e2","elType":"widget","settings":{"image":{"id":"3824","url":"https:\/\/ponceleon.site\/demos\/wp-content\/uploads\/sites\/84\/2021\/03\/spool-blk-illustrio.png"},"title_text":"This is the heading","description_text":"Click edit button to change this text. Lorem ipsum dolor sit amet, consectetur adipiscing elit. Ut elit tellus, luctus nec ullamcorper mattis, pulvinar dapibus leo.","image_size":{"unit":"%","size":"17"},"content_vertical_alignment":"middle","title_bottom_space":{"unit":"px","size":"20"},"title_color":"#020202","title_typography_typography":"custom","title_typography_font_family":"Poppins","title_typography_font_size":{"unit":"px","size":"15"},"title_typography_font_weight":"700","title_typography_text_transform":"uppercase","description_typography_typography":"custom","description_typography_font_family":"PT Serif","description_typography_font_size":{"unit":"px","size":"14"},"description_typography_line_height":{"unit":"em","size":"1.7"}},"elements":[],"widgetType":"image-box"}],"isInner":"1"}],"isInner":"1"},{"id":"a5944c","elType":"section","settings":{"content_width":{"unit":"px","size":"840"},"gap":"extended"},"elements":[{"id":"12ec91a3","elType":"column","settings":{"_column_size":"100"},"elements":[{"id":"75e026c4","elType":"widget","settings":{"text":"More Services","align":"center","size":"lg","typography_typography":"custom","typography_font_family":"Poppins","typography_font_size":{"unit":"px","size":"12"},"typography_font_weight":"600","typography_text_transform":"uppercase","typography_letter_spacing":{"unit":"px","size":"1"},"button_text_color":"#cea75a","background_color":"rgba(206,167,90,0)","hover_color":"#000000","button_background_hover_color":"rgba(229,229,229,0)","border_radius":{"unit":"px","top":"0","right":"0","bottom":"0","left":"0","isLinked":"1"},"_margin":{"unit":"px","top":"60","right":"0","bottom":"0","left":"0","isLinked":""},"_animation_delay":"600","typography_text_decoration":"underline"},"elements":[],"widgetType":"button"}],"isInner":"1"}],"isInner":"1"}],"isInner":""}],"isInner":""},{"id":"d2d667e","elType":"section","settings":{"gap":"extended","content_position":"middle","background_background":"classic","background_color":"#020202","background_overlay_background":"classic","background_overlay_opacity":{"unit":"px","size":"0.53"},"padding":{"unit":"px","top":"100","right":"0","bottom":"100","left":"0","isLinked":""},"background_overlay_position":"bottom right","background_overlay_size":"cover","shape_divider_top":"tilt","shape_divider_top_height":{"unit":"px","size":"61"},"shape_divider_top_flip":"yes","background_image":{"id":"3825","url":"https:\/\/ponceleon.site\/demos\/wp-content\/uploads\/sites\/84\/2021\/03\/d-ng-tr-n-qu-c-104958-unsplash.jpg"},"background_position":"center center","background_size":"cover","background_overlay_color":"#473b31","shape_divider_top_above_content":"yes","shape_divider_top_color":"#f9f9f9"},"elements":[{"id":"63763c2b","elType":"column","settings":{"_column_size":"100","_inline_size_tablet":"100"},"elements":[{"id":"52cce90a","elType":"widget","settings":{"slides":[{"content":"Donec lobortis orci consectetur mollis semper,lacus quis accumsan nunc orci non sem.","name":"Jane Doe","title":"CEO","image":{"id":"3826","url":"https:\/\/ponceleon.site\/demos\/wp-content\/uploads\/sites\/84\/2021\/03\/girl-people-landscape-sun-38554-1.jpeg"},"_id":"f2db2c0"},{"content":" Ut lacinia velit neque, et aliquet elit leo turpis, posuere a diam aliquam interdum orci.","name":"Annie Doe","title":"CEO","image":{"id":"3827","url":"https:\/\/ponceleon.site\/demos\/wp-content\/uploads\/sites\/84\/2021\/03\/pexels-photo-937481.jpeg"},"_id":"294641b"}],"layout":"image_above","width":{"unit":"%","size":"88"},"show_arrows":"","pagination":"fraction","content_color":"#ffffff","content_typography_typography":"custom","content_typography_font_family":"Playfair Display","content_typography_font_size":{"unit":"px","size":"32"},"content_typography_font_size_tablet":{"unit":"px","size":"25"},"content_typography_font_size_mobile":{"unit":"px","size":"18"},"content_typography_font_weight":"700","content_typography_font_style":"oblique","content_typography_line_height":{"unit":"em","size":"1.1"},"name_color":"#ffffff","name_typography_typography":"custom","name_typography_font_family":"Poppins","name_typography_font_size":{"unit":"px","size":"21"},"title_color":"rgba(255,255,255,0.75)","title_typography_typography":"custom","title_typography_font_family":"Poppins","title_typography_font_weight":"300","title_typography_font_style":"normal","image_size":{"unit":"px","size":"86"},"image_gap":{"unit":"px","size":"0"},"image_border":"yes","image_border_color":"#cea75a","image_border_width":{"unit":"px","size":"5"},"_margin":{"unit":"%","top":"","right":"","bottom":"","left":"","isLinked":""},"_animation":"fadeIn","animation_duration":"slow","name_typography_font_weight":"500","name_typography_text_transform":"uppercase","name_typography_font_style":"normal","title_typography_font_size":{"unit":"px","size":"14"},"title_typography_letter_spacing":{"unit":"px","size":"1.1"},"arrows_color":"#ffffff","pagination_color":"#ffffff"},"elements":[],"widgetType":"testimonial-carousel"}],"isInner":""}],"isInner":""}]},{"meta_id":"20905","post_id":"3811","meta_key":"_wp_page_template","meta_value":"elementor_canvas"},{"meta_id":"20913","post_id":"3811","meta_key":"_elementor_controls_usage","meta_value":"a:11:{s:11:\"text-editor\";a:3:{s:5:\"count\";i:8;s:15:\"control_percent\";i:4;s:8:\"controls\";a:3:{s:7:\"content\";a:1:{s:14:\"section_editor\";a:1:{s:6:\"editor\";i:8;}}s:5:\"style\";a:1:{s:13:\"section_style\";a:11:{s:5:\"align\";i:6;s:10:\"text_color\";i:8;s:21:\"typography_typography\";i:8;s:22:\"typography_font_family\";i:8;s:20:\"typography_font_size\";i:8;s:22:\"typography_font_weight\";i:2;s:25:\"typography_text_transform\";i:2;s:12:\"align_mobile\";i:2;s:25:\"typography_letter_spacing\";i:2;s:22:\"typography_line_height\";i:6;s:21:\"typography_font_style\";i:3;}}s:8:\"advanced\";a:4:{s:14:\"_section_style\";a:2:{s:7:\"_margin\";i:6;s:8:\"_padding\";i:5;}s:15:\"section_effects\";a:2:{s:10:\"_animation\";i:3;s:16:\"_animation_delay\";i:6;}s:19:\"_section_responsive\";a:1:{s:11:\"hide_mobile\";i:1;}s:15:\"_section_border\";a:2:{s:14:\"_border_border\";i:1;s:13:\"_border_width\";i:1;}}}}s:6:\"column\";a:3:{s:5:\"count\";i:22;s:15:\"control_percent\";i:0;s:8:\"controls\";a:2:{s:6:\"layout\";a:1:{s:6:\"layout\";a:2:{s:12:\"_inline_size\";i:3;s:19:\"_inline_size_tablet\";i:9;}}s:8:\"advanced\";a:1:{s:16:\"section_advanced\";a:4:{s:6:\"margin\";i:1;s:7:\"padding\";i:7;s:13:\"margin_mobile\";i:1;s:14:\"padding_tablet\";i:6;}}}}s:5:\"image\";a:3:{s:5:\"count\";i:2;s:15:\"control_percent\";i:3;s:8:\"controls\";a:3:{s:7:\"content\";a:1:{s:13:\"section_image\";a:4:{s:5:\"image\";i:2;s:10:\"image_size\";i:1;s:5:\"align\";i:1;s:12:\"align_tablet\";i:1;}}s:5:\"style\";a:1:{s:19:\"section_style_image\";a:3:{s:5:\"width\";i:2;s:7:\"opacity\";i:1;s:12:\"width_tablet\";i:1;}}s:8:\"advanced\";a:1:{s:14:\"_section_style\";a:3:{s:7:\"_margin\";i:1;s:8:\"_padding\";i:1;s:8:\"_z_index\";i:1;}}}}s:7:\"section\";a:3:{s:5:\"count\";i:14;s:15:\"control_percent\";i:4;s:8:\"controls\";a:3:{s:6:\"layout\";a:2:{s:14:\"section_layout\";a:3:{s:3:\"gap\";i:13;s:16:\"content_position\";i:3;s:13:\"content_width\";i:5;}s:17:\"section_structure\";a:1:{s:9:\"structure\";i:5;}}s:8:\"advanced\";a:2:{s:15:\"section_effects\";a:3:{s:9:\"animation\";i:1;s:18:\"animation_duration\";i:1;s:15:\"animation_delay\";i:1;}s:16:\"section_advanced\";a:3:{s:7:\"padding\";i:4;s:14:\"padding_tablet\";i:2;s:6:\"margin\";i:1;}}s:5:\"style\";a:4:{s:18:\"section_background\";a:5:{s:21:\"background_background\";i:4;s:19:\"background_position\";i:2;s:15:\"background_size\";i:2;s:16:\"background_color\";i:4;s:16:\"background_image\";i:1;}s:26:\"section_background_overlay\";a:7:{s:29:\"background_overlay_background\";i:2;s:24:\"background_overlay_color\";i:2;s:26:\"background_overlay_opacity\";i:2;s:24:\"background_overlay_image\";i:1;s:23:\"background_overlay_size\";i:2;s:18:\"overlay_blend_mode\";i:1;s:27:\"background_overlay_position\";i:1;}s:21:\"section_shape_divider\";a:9:{s:20:\"shape_divider_bottom\";i:1;s:27:\"shape_divider_bottom_height\";i:1;s:25:\"shape_divider_bottom_flip\";i:1;s:24:\"shape_divider_top_height\";i:2;s:26:\"shape_divider_top_negative\";i:1;s:17:\"shape_divider_top\";i:1;s:22:\"shape_divider_top_flip\";i:1;s:31:\"shape_divider_top_above_content\";i:1;s:23:\"shape_divider_top_color\";i:1;}s:14:\"section_border\";a:3:{s:13:\"border_border\";i:1;s:12:\"border_width\";i:1;s:12:\"border_color\";i:1;}}}}s:17:\"animated-headline\";a:3:{s:5:\"count\";i:1;s:15:\"control_percent\";i:8;s:8:\"controls\";a:3:{s:7:\"content\";a:1:{s:13:\"text_elements\";a:6:{s:14:\"headline_style\";i:1;s:14:\"animation_type\";i:1;s:11:\"before_text\";i:1;s:16:\"highlighted_text\";i:1;s:13:\"rotating_text\";i:1;s:3:\"tag\";i:1;}}s:5:\"style\";a:1:{s:18:\"section_style_text\";a:14:{s:11:\"title_color\";i:1;s:27:\"title_typography_typography\";i:1;s:28:\"title_typography_font_family\";i:1;s:26:\"title_typography_font_size\";i:1;s:33:\"title_typography_font_size_tablet\";i:1;s:33:\"title_typography_font_size_mobile\";i:1;s:28:\"title_typography_font_weight\";i:1;s:31:\"title_typography_text_transform\";i:1;s:31:\"title_typography_letter_spacing\";i:1;s:11:\"words_color\";i:1;s:27:\"words_typography_typography\";i:1;s:28:\"words_typography_font_family\";i:1;s:28:\"words_typography_font_weight\";i:1;s:31:\"words_typography_text_transform\";i:1;}}s:8:\"advanced\";a:2:{s:14:\"_section_style\";a:2:{s:7:\"_margin\";i:1;s:14:\"_margin_mobile\";i:1;}s:15:\"section_effects\";a:2:{s:10:\"_animation\";i:1;s:18:\"animation_duration\";i:1;}}}}s:7:\"divider\";a:3:{s:5:\"count\";i:3;s:15:\"control_percent\";i:2;s:8:\"controls\";a:3:{s:5:\"style\";a:1:{s:21:\"section_divider_style\";a:2:{s:6:\"weight\";i:3;s:5:\"color\";i:3;}}s:7:\"content\";a:1:{s:15:\"section_divider\";a:2:{s:5:\"width\";i:3;s:5:\"align\";i:3;}}s:8:\"advanced\";a:1:{s:15:\"section_effects\";a:3:{s:10:\"_animation\";i:3;s:18:\"animation_duration\";i:3;s:16:\"_animation_delay\";i:3;}}}}s:6:\"button\";a:3:{s:5:\"count\";i:4;s:15:\"control_percent\";i:6;s:8:\"controls\";a:3:{s:7:\"content\";a:1:{s:14:\"section_button\";a:4:{s:4:\"text\";i:4;s:5:\"align\";i:4;s:4:\"size\";i:4;s:12:\"align_mobile\";i:2;}}s:5:\"style\";a:1:{s:13:\"section_style\";a:16:{s:21:\"typography_typography\";i:4;s:22:\"typography_font_family\";i:4;s:20:\"typography_font_size\";i:4;s:22:\"typography_font_weight\";i:4;s:25:\"typography_text_transform\";i:4;s:25:\"typography_letter_spacing\";i:4;s:17:\"button_text_color\";i:4;s:16:\"background_color\";i:4;s:11:\"hover_color\";i:4;s:29:\"button_background_hover_color\";i:4;s:13:\"border_radius\";i:4;s:25:\"button_hover_border_color\";i:2;s:13:\"border_border\";i:2;s:12:\"border_width\";i:2;s:12:\"border_color\";i:1;s:26:\"typography_text_decoration\";i:2;}}s:8:\"advanced\";a:2:{s:15:\"section_effects\";a:2:{s:10:\"_animation\";i:2;s:16:\"_animation_delay\";i:4;}s:14:\"_section_style\";a:1:{s:7:\"_margin\";i:2;}}}}s:7:\"heading\";a:3:{s:5:\"count\";i:2;s:15:\"control_percent\";i:5;s:8:\"controls\";a:3:{s:7:\"content\";a:1:{s:13:\"section_title\";a:2:{s:5:\"title\";i:2;s:5:\"align\";i:2;}}s:5:\"style\";a:1:{s:19:\"section_title_style\";a:9:{s:11:\"title_color\";i:2;s:21:\"typography_typography\";i:2;s:22:\"typography_font_family\";i:2;s:20:\"typography_font_size\";i:2;s:22:\"typography_font_weight\";i:2;s:25:\"typography_text_transform\";i:2;s:25:\"typography_letter_spacing\";i:2;s:27:\"typography_font_size_tablet\";i:2;s:27:\"typography_font_size_mobile\";i:2;}}s:8:\"advanced\";a:2:{s:14:\"_section_style\";a:1:{s:7:\"_margin\";i:2;}s:15:\"section_effects\";a:2:{s:10:\"_animation\";i:2;s:18:\"animation_duration\";i:2;}}}}s:6:\"slides\";a:3:{s:5:\"count\";i:1;s:15:\"control_percent\";i:7;s:8:\"controls\";a:2:{s:7:\"content\";a:2:{s:14:\"section_slides\";a:4:{s:6:\"slides\";i:1;s:13:\"slides_height\";i:1;s:20:\"slides_height_tablet\";i:1;s:20:\"slides_height_mobile\";i:1;}s:22:\"section_slider_options\";a:3:{s:10:\"navigation\";i:1;s:14:\"pause_on_hover\";i:1;s:17:\"content_animation\";i:1;}}s:5:\"style\";a:4:{s:20:\"section_style_slides\";a:1:{s:17:\"content_max_width\";i:1;}s:19:\"section_style_title\";a:7:{s:15:\"heading_spacing\";i:1;s:13:\"heading_color\";i:1;s:29:\"heading_typography_typography\";i:1;s:30:\"heading_typography_font_family\";i:1;s:28:\"heading_typography_font_size\";i:1;s:30:\"heading_typography_font_weight\";i:1;s:33:\"heading_typography_text_transform\";i:1;}s:25:\"section_style_description\";a:7:{s:19:\"description_spacing\";i:1;s:17:\"description_color\";i:1;s:33:\"description_typography_typography\";i:1;s:34:\"description_typography_font_family\";i:1;s:32:\"description_typography_font_size\";i:1;s:33:\"description_typography_font_style\";i:1;s:34:\"description_typography_line_height\";i:1;}s:24:\"section_style_navigation\";a:1:{s:10:\"dots_color\";i:1;}}}}s:9:\"image-box\";a:3:{s:5:\"count\";i:6;s:15:\"control_percent\";i:5;s:8:\"controls\";a:2:{s:7:\"content\";a:1:{s:13:\"section_image\";a:3:{s:5:\"image\";i:6;s:10:\"title_text\";i:6;s:16:\"description_text\";i:6;}}s:5:\"style\";a:2:{s:19:\"section_style_image\";a:1:{s:10:\"image_size\";i:6;}s:21:\"section_style_content\";a:12:{s:26:\"content_vertical_alignment\";i:6;s:18:\"title_bottom_space\";i:6;s:11:\"title_color\";i:6;s:27:\"title_typography_typography\";i:6;s:28:\"title_typography_font_family\";i:6;s:26:\"title_typography_font_size\";i:6;s:28:\"title_typography_font_weight\";i:6;s:31:\"title_typography_text_transform\";i:6;s:33:\"description_typography_typography\";i:6;s:34:\"description_typography_font_family\";i:6;s:32:\"description_typography_font_size\";i:6;s:34:\"description_typography_line_height\";i:6;}}}}s:20:\"testimonial-carousel\";a:3:{s:5:\"count\";i:1;s:15:\"control_percent\";i:11;s:8:\"controls\";a:3:{s:7:\"content\";a:2:{s:14:\"section_slides\";a:3:{s:6:\"slides\";i:1;s:6:\"layout\";i:1;s:5:\"width\";i:1;}s:26:\"section_additional_options\";a:2:{s:11:\"show_arrows\";i:1;s:10:\"pagination\";i:1;}}s:5:\"style\";a:3:{s:21:\"section_content_style\";a:23:{s:13:\"content_color\";i:1;s:29:\"content_typography_typography\";i:1;s:30:\"content_typography_font_family\";i:1;s:28:\"content_typography_font_size\";i:1;s:35:\"content_typography_font_size_tablet\";i:1;s:35:\"content_typography_font_size_mobile\";i:1;s:30:\"content_typography_font_weight\";i:1;s:29:\"content_typography_font_style\";i:1;s:30:\"content_typography_line_height\";i:1;s:10:\"name_color\";i:1;s:26:\"name_typography_typography\";i:1;s:27:\"name_typography_font_family\";i:1;s:25:\"name_typography_font_size\";i:1;s:11:\"title_color\";i:1;s:27:\"title_typography_typography\";i:1;s:28:\"title_typography_font_family\";i:1;s:28:\"title_typography_font_weight\";i:1;s:27:\"title_typography_font_style\";i:1;s:27:\"name_typography_font_weight\";i:1;s:30:\"name_typography_text_transform\";i:1;s:26:\"name_typography_font_style\";i:1;s:26:\"title_typography_font_size\";i:1;s:31:\"title_typography_letter_spacing\";i:1;}s:19:\"section_image_style\";a:5:{s:10:\"image_size\";i:1;s:9:\"image_gap\";i:1;s:12:\"image_border\";i:1;s:18:\"image_border_color\";i:1;s:18:\"image_border_width\";i:1;}s:18:\"section_navigation\";a:2:{s:12:\"arrows_color\";i:1;s:16:\"pagination_color\";i:1;}}s:8:\"advanced\";a:2:{s:14:\"_section_style\";a:1:{s:7:\"_margin\";i:1;}s:15:\"section_effects\";a:2:{s:10:\"_animation\";i:1;s:18:\"animation_duration\";i:1;}}}}}"},{"meta_id":"20931","post_id":"3811","meta_key":"_thumbnail_id","meta_value":"6360"},{"meta_id":"40306","post_id":"3811","meta_key":"imagen_larga","meta_value":"6360"},{"meta_id":"40307","post_id":"3811","meta_key":"_imagen_larga","meta_value":"field_6043b5afc4b0a"},{"meta_id":"40308","post_id":"3811","meta_key":"imagen_corta","meta_value":"6953"},{"meta_id":"40309","post_id":"3811","meta_key":"_imagen_corta","meta_value":"field_6050ddfaadfc1"},{"meta_id":"40294","post_id":"3811","meta_key":"_elementor_css","meta_value":"a:6:{s:4:\"time\";i:1615941808;s:5:\"fonts\";a:3:{i:0;s:7:\"Poppins\";i:2;s:16:\"Playfair Display\";i:4;s:8:\"PT Serif\";}s:5:\"icons\";a:1:{i:0;s:0:\"\";}s:20:\"dynamic_elements_ids\";a:0:{}s:6:\"status\";s:4:\"file\";i:0;s:0:\"\";}"}]