[{"meta_id":"22557","post_id":"4154","meta_key":"_edit_lock","meta_value":"1615985137:32"},{"meta_id":"22558","post_id":"4154","meta_key":"_edit_last","meta_value":"32"},{"meta_id":"22559","post_id":"4154","meta_key":"categorizar","meta_value":"a:10:{i:0;s:2:\"44\";i:1;s:2:\"50\";i:2;s:2:\"54\";i:3;s:2:\"43\";i:4;s:2:\"66\";i:5;s:2:\"67\";i:6;s:2:\"36\";i:7;s:2:\"40\";i:8;s:2:\"38\";i:9;s:2:\"34\";}"},{"meta_id":"22560","post_id":"4154","meta_key":"_categorizar","meta_value":"field_602d8e8b988e5"},{"meta_id":"22563","post_id":"4154","meta_key":"_elementor_edit_mode","meta_value":"builder"},{"meta_id":"22564","post_id":"4154","meta_key":"_elementor_template_type","meta_value":"wp-page"},{"meta_id":"22565","post_id":"4154","meta_key":"_elementor_version","meta_value":"3.1.1"},{"meta_id":"22566","post_id":"4154","meta_key":"_elementor_pro_version","meta_value":"3.1.0"},{"meta_id":"22667","post_id":"4154","meta_key":"_elementor_data","meta_value":[{"id":"204cfd5","elType":"section","settings":{"padding":{"unit":"px","top":"40","right":"40","bottom":"0","left":"40","isLinked":""},"padding_tablet":{"unit":"px","top":"60","right":"20","bottom":"60","left":"20","isLinked":""},"layout":"full_width","background_image":{"id":"4157","url":"https:\/\/ponceleon.site\/demos\/wp-content\/uploads\/sites\/84\/2021\/03\/Untitled-2.jpg"},"background_position":"center center","background_repeat":"no-repeat","background_size":"cover","margin":{"unit":"px","top":"0","right":"0","bottom":"0","left":"0","isLinked":""},"padding_mobile":{"unit":"em","top":"0","right":"0","bottom":"0","left":"0","isLinked":""}},"elements":[{"id":"6ccb7037","elType":"column","settings":{"_column_size":"100","_inline_size_tablet":"100","content_position":"top","margin":{"unit":"px","top":"0","right":"0","bottom":"0","left":"0","isLinked":""},"margin_tablet":{"unit":"px","top":"0","right":"0","bottom":"0","left":"0","isLinked":""},"padding":{"unit":"px","top":"0","right":"0","bottom":"0","left":"0","isLinked":""},"margin_mobile":{"unit":"px","top":"0","right":"0","bottom":"0","left":"0","isLinked":""},"padding_mobile":{"unit":"px","top":"0","right":"0","bottom":"0","left":"0","isLinked":""}},"elements":[{"id":"6736d5db","elType":"section","settings":{"structure":"20","z_index":"2","background_background":"classic","background_color":"#f4f5f7","padding":{"unit":"px","top":"80","right":"0","bottom":"80","left":"80","isLinked":""},"margin_mobile":{"unit":"px","top":"0","right":"0","bottom":"0","left":"0","isLinked":""},"padding_mobile":{"unit":"px","top":"30","right":"30","bottom":"30","left":"30","isLinked":""},"shape_divider_bottom_width":{"unit":"%","size":"135"},"shape_divider_bottom_height":{"unit":"px","size":"295"},"shape_divider_bottom_negative":"yes","margin_tablet":{"unit":"px","top":"0","right":"0","bottom":"0","left":"0","isLinked":"1"},"padding_tablet":{"unit":"em","top":"2","right":"2","bottom":"2","left":"2","isLinked":"1"}},"elements":[{"id":"70f4817b","elType":"column","settings":{"_column_size":"50","_inline_size_tablet":"100","margin":{"unit":"px","top":"0","right":"80","bottom":"0","left":"0","isLinked":""},"padding":{"unit":"px","top":"0","right":"0","bottom":"90","left":"0","isLinked":""},"margin_tablet":{"unit":"px","top":"0","right":"0","bottom":"0","left":"0","isLinked":""},"margin_mobile":{"unit":"px","top":"0","right":"0","bottom":"0","left":"0","isLinked":""},"padding_mobile":{"unit":"px","top":"0","right":"0","bottom":"40","left":"0","isLinked":""}},"elements":[{"id":"685cc6e8","elType":"widget","settings":{"title":"Modernize Your Web Design","header_size":"h1","align":"left","align_tablet":"center","title_color":"#000000","typography_typography":"custom","typography_font_family":"Fredoka One","typography_font_size":{"unit":"rem","size":"4"},"typography_text_transform":"capitalize","typography_line_height":{"unit":"em","size":"1.2"},"_margin":{"unit":"px","top":"0","right":"0","bottom":"30","left":"0","isLinked":""},"typography_font_size_mobile":{"unit":"px","size":"30"},"typography_line_height_mobile":{"unit":"px","size":"40"},"_animation":"fadeIn","typography_font_weight":"100","typography_letter_spacing":{"unit":"px","size":"-1"}},"elements":[],"widgetType":"heading"},{"id":"4285dd81","elType":"widget","settings":{"space":{"unit":"px","size":"42"}},"elements":[],"widgetType":"spacer"},{"id":"5bf047dc","elType":"widget","settings":{"align":"left","text_color":"#000000","typography_typography":"custom","typography_font_family":"Nunito","typography_font_size":{"unit":"px","size":"16"},"typography_line_height":{"unit":"px","size":"24"},"editor":"<p>Te maiorum pericula neglegentur sit, pro fabulas iracundia ad. Ne vim facilis feugait moderatius, nec eu perpetua scriptorem referrentur. Ut alii delicata mei. Cum case maluisset liberavisse ad.<\/p>","align_tablet":"center","_margin":{"unit":"px","top":"0","right":"0","bottom":"60","left":"0","isLinked":""},"typography_font_style":"oblique","_padding":{"unit":"em","top":"0","right":"3","bottom":"0","left":"0","isLinked":""}},"elements":[],"widgetType":"text-editor"},{"id":"7885c12c","elType":"widget","settings":{"text":"Go to Projects","align":"left","size":"md","icon_align":"right","icon_indent":{"unit":"px","size":"14"},"typography_typography":"custom","typography_font_family":"Poppins","typography_font_size":{"unit":"px","size":"14"},"typography_font_weight":"600","typography_text_transform":"uppercase","typography_letter_spacing":{"unit":"px","size":"0.5"},"button_text_color":"#ffffff","background_color":"#2572ff","hover_color":"#ffffff","button_background_hover_color":"#e032a6","border_radius":{"unit":"px","top":"30","right":"30","bottom":"30","left":"30","isLinked":"1"},"text_padding":{"unit":"px","top":"20","right":"40","bottom":"20","left":"40","isLinked":""},"border_width":{"unit":"px","top":"2","right":"2","bottom":"2","left":"2","isLinked":"1"},"align_tablet":"center","_margin":{"unit":"px","top":"30","right":"0","bottom":"0","left":"0","isLinked":""},"_margin_mobile":{"unit":"px","top":"0","right":"0","bottom":"0","left":"0","isLinked":""},"_padding":{"unit":"px","top":"0","right":"0","bottom":"0","left":"0","isLinked":"1"},"_animation":"fadeIn"},"elements":[],"widgetType":"button"}],"isInner":"1"},{"id":"72c0cee0","elType":"column","settings":{"_column_size":"50","_inline_size_tablet":"100","content_position":"bottom","margin":{"unit":"px","top":"0","right":"0","bottom":"0","left":"0","isLinked":""},"padding":{"unit":"px","top":"0","right":"0","bottom":"0","left":"0","isLinked":""},"background_background":"classic","background_image":{"id":"4158","url":"https:\/\/ponceleon.site\/demos\/wp-content\/uploads\/sites\/84\/2021\/03\/shape-gradienta1.png"},"background_size":"cover","background_bg_width":{"unit":"%","size":"120"}},"elements":[{"id":"56f29ab8","elType":"widget","settings":{"carousel":[{"id":"4159","url":"https:\/\/ponceleon.site\/demos\/wp-content\/uploads\/sites\/84\/2021\/03\/image-from-rawpixel-id-478019-deriv-trial.png"},{"id":"4160","url":"https:\/\/ponceleon.site\/demos\/wp-content\/uploads\/sites\/84\/2021\/03\/image-from-rawpixel-id-456067-deriv-1.png"}],"thumbnail_size":"full","slides_to_show":"1","slides_to_scroll":"1","navigation":"none","dots_size":{"unit":"px","size":"10"},"dots_color":"#2572ff","image_border_radius":{"unit":"px","top":"4","right":"4","bottom":"4","left":"4","isLinked":"1"},"_margin_mobile":{"unit":"px","top":"0","right":"0","bottom":"0","left":"0","isLinked":""},"_animation":"fadeIn","_box_shadow_box_shadow":{"horizontal":"-10","vertical":"-10","blur":"50","spread":"0","color":"rgba(0,0,0,0.1)"},"pause_on_hover":"no","effect":"fade","autoplay_speed":"6000"},"elements":[],"widgetType":"image-carousel"}],"isInner":"1"}],"isInner":"1"}],"isInner":""}],"isInner":""},{"id":"2eac19dd","elType":"section","settings":{"structure":"30","margin":{"unit":"px","top":"0","right":"0","bottom":"0","left":"0","isLinked":""},"z_index":"2","margin_mobile":{"unit":"px","top":"40","right":"0","bottom":"0","left":"0","isLinked":""},"padding_tablet":{"unit":"px","top":"0","right":"20","bottom":"0","left":"20","isLinked":""},"background_background":"classic","background_color":"#ffffff","border_border":"solid","border_width":{"unit":"px","top":"0","right":"40","bottom":"0","left":"40","isLinked":""},"border_color":"#ffffff","shape_divider_top":"curve-asymmetrical","shape_divider_top_color":"#f4f5f7","shape_divider_top_width":{"unit":"%","size":"100"},"shape_divider_top_height":{"unit":"px","size":"220"}},"elements":[{"id":"2b52f3da","elType":"column","settings":{"_column_size":"33","margin":{"unit":"px","top":"0","right":"40","bottom":"0","left":"0","isLinked":""},"padding":{"unit":"px","top":"0","right":"0","bottom":"0","left":"0","isLinked":""},"_inline_size_tablet":"33","margin_tablet":{"unit":"px","top":"0","right":"0","bottom":"0","left":"0","isLinked":""},"padding_tablet":{"unit":"px","top":"0","right":"0","bottom":"0","left":"0","isLinked":""},"animation":"fadeIn"},"elements":[{"id":"4cbe86a","elType":"widget","settings":{"space":{"unit":"px","size":"236"},"_background_background":"classic","_background_image":{"id":"4161","url":"https:\/\/ponceleon.site\/demos\/wp-content\/uploads\/sites\/84\/2021\/03\/screenshot-8-1550492713-300x802-1.jpg"},"_border_radius":{"unit":"px","top":"6","right":"6","bottom":"6","left":"6","isLinked":"1"},"_box_shadow_box_shadow_type":"yes","_box_shadow_box_shadow":{"horizontal":"-10","vertical":"-10","blur":"49","spread":"-4","color":"rgba(0,0,0,0.07)"},"_margin":{"unit":"px","top":"0","right":"120","bottom":"0","left":"0","isLinked":""},"_background_position":"top center","_background_size":"cover","space_tablet":{"unit":"px","size":"153"},"_margin_tablet":{"unit":"px","top":"-17","right":"40","bottom":"0","left":"0","isLinked":""}},"elements":[],"widgetType":"spacer"}],"isInner":""},{"id":"518f5ec","elType":"column","settings":{"_column_size":"33","margin":{"unit":"px","top":"0","right":"0","bottom":"0","left":"0","isLinked":""},"_inline_size_tablet":"33","margin_tablet":{"unit":"px","top":"0","right":"0","bottom":"0","left":"0","isLinked":""},"padding_tablet":{"unit":"px","top":"0","right":"0","bottom":"0","left":"0","isLinked":""},"animation":"fadeIn"},"elements":[{"id":"71aafd32","elType":"widget","settings":{"space":{"unit":"px","size":"415"},"_background_background":"classic","_background_image":{"id":"4162","url":"https:\/\/ponceleon.site\/demos\/wp-content\/uploads\/sites\/84\/2021\/03\/screenshot-6-1550491570-300x883-1.jpg"},"_border_radius":{"unit":"px","top":"6","right":"6","bottom":"6","left":"6","isLinked":"1"},"_box_shadow_box_shadow_type":"yes","_box_shadow_box_shadow":{"horizontal":"-10","vertical":"-10","blur":"49","spread":"-4","color":"rgba(0,0,0,0.07)"},"_margin":{"unit":"px","top":"0","right":"63","bottom":"0","left":"0","isLinked":""},"_background_position":"top center","_background_size":"cover","space_tablet":{"unit":"px","size":"245"},"_margin_tablet":{"unit":"px","top":"-38","right":"0","bottom":"0","left":"0","isLinked":""}},"elements":[],"widgetType":"spacer"}],"isInner":""},{"id":"7d5199f2","elType":"column","settings":{"_column_size":"33","margin":{"unit":"px","top":"0","right":"0","bottom":"0","left":"40","isLinked":""},"padding":{"unit":"px","top":"0","right":"0","bottom":"0","left":"0","isLinked":""},"_inline_size_tablet":"33","margin_tablet":{"unit":"px","top":"0","right":"0","bottom":"0","left":"0","isLinked":""},"padding_tablet":{"unit":"px","top":"0","right":"0","bottom":"0","left":"0","isLinked":""},"animation":"fadeIn"},"elements":[{"id":"7b86edd9","elType":"widget","settings":{"space":{"unit":"px","size":"327"},"_background_background":"classic","_background_image":{"id":"4163","url":"https:\/\/ponceleon.site\/demos\/wp-content\/uploads\/sites\/84\/2021\/03\/screenshot-244-1550499512-300x907-1.jpg"},"_border_radius":{"unit":"px","top":"6","right":"6","bottom":"6","left":"6","isLinked":"1"},"_box_shadow_box_shadow_type":"yes","_box_shadow_box_shadow":{"horizontal":"-10","vertical":"-10","blur":"49","spread":"-4","color":"rgba(0,0,0,0.07)"},"_margin":{"unit":"px","top":"0","right":"40","bottom":"0","left":"40","isLinked":""},"space_tablet":{"unit":"px","size":"160"},"_margin_tablet":{"unit":"px","top":"-19","right":"0","bottom":"0","left":"20","isLinked":""}},"elements":[],"widgetType":"spacer"}],"isInner":""}],"isInner":""},{"id":"3878e375","elType":"section","settings":{"structure":"20","padding":{"unit":"px","top":"140","right":"0","bottom":"80","left":"0","isLinked":""},"background_background":"classic","background_position":"initial","background_size":"initial","background_xpos":{"unit":"px","size":"-75"},"background_ypos":{"unit":"px","size":"-800"},"background_bg_width":{"unit":"vw","size":"54"},"z_index":"8","background_color":"#ffffff","background_color_b":"#e0358b","background_gradient_angle":{"unit":"deg","size":"90"},"background_overlay_image":{"id":"4164","url":"https:\/\/ponceleon.site\/demos\/wp-content\/uploads\/sites\/84\/2021\/03\/shape-white.png"},"background_overlay_position":"top center","background_overlay_repeat":"no-repeat","background_overlay_size":"cover","background_overlay_opacity":{"unit":"px","size":"1"},"shape_divider_top_color":"#e2e9ff","shape_divider_top_width":{"unit":"%","size":"90"},"shape_divider_top_height":{"unit":"px","size":"98"},"padding_mobile":{"unit":"px","top":"60","right":"20","bottom":"60","left":"20","isLinked":""},"margin_tablet":{"unit":"px","top":"0","right":"0","bottom":"0","left":"0","isLinked":"1"},"padding_tablet":{"unit":"px","top":"0","right":"0","bottom":"0","left":"0","isLinked":"1"}},"elements":[{"id":"5a888c2e","elType":"column","settings":{"_column_size":"50","_inline_size":"50","content_position":"center","background_position":"center right","background_repeat":"no-repeat","background_size":"contain","_inline_size_tablet":"100","background_background":"classic","background_overlay_background":"classic","background_overlay_image":{"id":"4165","url":"https:\/\/ponceleon.site\/demos\/wp-content\/uploads\/sites\/84\/2021\/03\/shape-gradient2.png"},"background_overlay_position":"center center","background_overlay_repeat":"no-repeat","background_overlay_size":"contain","background_overlay_opacity":{"unit":"px","size":"0.08"},"css_filters_css_filter":"custom","css_filters_saturate":{"unit":"px","size":"0"},"padding":{"unit":"%","top":"10","right":"10","bottom":"10","left":"10","isLinked":""}},"elements":[{"id":"62d4c551","elType":"section","settings":{"structure":"30","margin":{"unit":"px","top":"0","right":"0","bottom":"0","left":"0","isLinked":""},"margin_tablet":{"unit":"px","top":"30","right":"0","bottom":"0","left":"0","isLinked":""},"animation":"fadeIn"},"elements":[{"id":"4727ba4c","elType":"column","settings":{"_column_size":"33","_inline_size_tablet":"50","content_position":"bottom"},"elements":[{"id":"6a32cb97","elType":"widget","settings":{"image":{"id":"4166","url":"https:\/\/ponceleon.site\/demos\/wp-content\/uploads\/sites\/84\/2021\/03\/on_image_like.png"},"image_border_radius":{"unit":"px","top":"4","right":"4","bottom":"4","left":"4","isLinked":"1"},"image_box_shadow_box_shadow_type":"yes","image_box_shadow_box_shadow":{"horizontal":"-10","vertical":"-10","blur":"50","spread":"0","color":"rgba(0,0,0,0.1)"},"width":{"unit":"%","size":"52"},"_margin":{"unit":"px","top":"0","right":"0","bottom":"-44","left":"0","isLinked":""}},"elements":[],"widgetType":"image"}],"isInner":"1"},{"id":"6ae23543","elType":"column","settings":{"_column_size":"33","_inline_size":"28.32","_inline_size_tablet":"50","content_position":"center"},"elements":[{"id":"70a9c16d","elType":"widget","settings":{"image":{"id":"4167","url":"https:\/\/ponceleon.site\/demos\/wp-content\/uploads\/sites\/84\/2021\/03\/under_image.png"},"image_border_radius":{"unit":"px","top":"4","right":"4","bottom":"4","left":"4","isLinked":"1"},"image_box_shadow_box_shadow_type":"yes","image_box_shadow_box_shadow":{"horizontal":"-10","vertical":"-10","blur":"50","spread":"0","color":"rgba(0,0,0,0.1)"},"align":"left","width":{"unit":"%","size":"88"}},"elements":[],"widgetType":"image"}],"isInner":"1"},{"id":"4071a71e","elType":"column","settings":{"_column_size":"33","_inline_size":"38.342","_inline_size_tablet":"50","margin_tablet":{"unit":"px","top":"40","right":"0","bottom":"0","left":"0","isLinked":""}},"elements":[{"id":"1b006219","elType":"widget","settings":{"image":{"id":"4168","url":"https:\/\/ponceleon.site\/demos\/wp-content\/uploads\/sites\/84\/2021\/03\/on_image.png"},"image_border_radius":{"unit":"px","top":"4","right":"4","bottom":"4","left":"4","isLinked":"1"},"image_box_shadow_box_shadow_type":"yes","image_box_shadow_box_shadow":{"horizontal":"-10","vertical":"-10","blur":"50","spread":"0","color":"rgba(0,0,0,0.1)"},"align":"left","width":{"unit":"%","size":"82"}},"elements":[],"widgetType":"image"}],"isInner":"1"}],"isInner":"1"},{"id":"70f718bc","elType":"section","settings":{"structure":"30","margin_tablet":{"unit":"px","top":"0","right":"0","bottom":"0","left":"0","isLinked":""},"animation":"fadeIn","margin":{"unit":"px","top":"0","right":"0","bottom":"0","left":"0","isLinked":"1"}},"elements":[{"id":"dfc7e6f","elType":"column","settings":{"_column_size":"33","_inline_size_tablet":"50","margin_tablet":{"unit":"px","top":"40","right":"0","bottom":"0","left":"0","isLinked":""}},"elements":[],"isInner":"1"},{"id":"4f20f4c","elType":"column","settings":{"_column_size":"33","_inline_size_tablet":"50","margin_tablet":{"unit":"px","top":"40","right":"0","bottom":"0","left":"0","isLinked":""}},"elements":[{"id":"334f7fe7","elType":"widget","settings":{"image":{"id":"4169","url":"https:\/\/ponceleon.site\/demos\/wp-content\/uploads\/sites\/84\/2021\/03\/default.png"},"image_border_radius":{"unit":"px","top":"4","right":"4","bottom":"4","left":"4","isLinked":"1"},"image_box_shadow_box_shadow_type":"yes","image_box_shadow_box_shadow":{"horizontal":"-10","vertical":"-10","blur":"50","spread":"0","color":"rgba(0,0,0,0.1)"},"align":"left","width":{"unit":"%","size":"93"}},"elements":[],"widgetType":"image"}],"isInner":"1"},{"id":"16a8fe86","elType":"column","settings":{"_column_size":"33","_inline_size_tablet":"50","margin_tablet":{"unit":"px","top":"40","right":"0","bottom":"0","left":"0","isLinked":""},"content_position":"center"},"elements":[{"id":"7e579daa","elType":"widget","settings":{"image":{"id":"4170","url":"https:\/\/ponceleon.site\/demos\/wp-content\/uploads\/sites\/84\/2021\/03\/masonry_border.png"},"image_border_radius":{"unit":"px","top":"4","right":"4","bottom":"4","left":"4","isLinked":"1"},"image_box_shadow_box_shadow_type":"yes","image_box_shadow_box_shadow":{"horizontal":"-10","vertical":"-10","blur":"50","spread":"0","color":"rgba(0,0,0,0.1)"},"align":"left","width":{"unit":"%","size":"60"},"_margin":{"unit":"px","top":"0","right":"0","bottom":"0","left":"0","isLinked":""}},"elements":[],"widgetType":"image"}],"isInner":"1"}],"isInner":"1"}],"isInner":""},{"id":"663029d6","elType":"column","settings":{"_column_size":"50","_inline_size":"50","_inline_size_tablet":"100","content_position":"top","margin":{"unit":"px","top":"0","right":"0","bottom":"0","left":"0","isLinked":""},"margin_tablet":{"unit":"px","top":"0","right":"0","bottom":"0","left":"0","isLinked":""},"animation":"fadeIn","padding":{"unit":"em","top":"5","right":"3","bottom":"5","left":"5","isLinked":""}},"elements":[{"id":"639dd6f2","elType":"widget","settings":{"title":"Awesome Features","align":"left","align_tablet":"center","title_color":"#4054b2","typography_typography":"custom","typography_font_family":"Nunito","typography_font_size":{"unit":"px","size":"18"},"typography_text_transform":"capitalize","typography_line_height":{"unit":"px","size":"30"},"header_size":"h4","_margin":{"unit":"px","top":"0","right":"0","bottom":"-10","left":"0","isLinked":""},"_padding":{"unit":"px","top":"0","right":"0","bottom":"0","left":"0","isLinked":""},"typography_font_weight":"400","typography_font_style":"italic"},"elements":[],"widgetType":"heading"},{"id":"704b0bb5","elType":"widget","settings":{"title":"Fully Responsive","align":"left","align_tablet":"center","title_color":"#4054b2","typography_typography":"custom","typography_font_family":"Fredoka One","typography_font_size":{"unit":"rem","size":"2.5"},"typography_text_transform":"capitalize","typography_line_height":{"unit":"em","size":"1.4"},"typography_font_weight":"100","_animation":"fadeIn"},"elements":[],"widgetType":"heading"},{"id":"3a2cbc93","elType":"widget","settings":{"align":"left","typography_typography":"custom","typography_font_family":"Nunito","typography_font_size":{"unit":"px","size":"16"},"typography_line_height":{"unit":"px","size":"24"},"editor":"<p>Provide your mobile users with the best experience by sharing the most detailed images.<\/p><p>Lorem ipsum dolor sit amet, consectetur adipiscing elit. Ut elit tellus, luctus nec ullamcorper mattis, pulvinar dapibus leo.<\/p>","align_tablet":"center"},"elements":[],"widgetType":"text-editor"},{"id":"7aefc9c0","elType":"widget","settings":{"text":"Test Now","align":"left","size":"md","icon":"fa fa-arrow-right","icon_align":"right","icon_indent":{"unit":"px","size":"21"},"typography_typography":"custom","typography_font_family":"Nunito","typography_font_size":{"unit":"px","size":"14"},"typography_font_weight":"900","typography_text_transform":"uppercase","typography_letter_spacing":{"unit":"px","size":"0.5"},"button_text_color":"#2572ff","background_color":"#ffffff","hover_color":"#ffffff","button_background_hover_color":"#2572ff","border_radius":{"unit":"px","top":"50","right":"50","bottom":"50","left":"50","isLinked":"1"},"text_padding":{"unit":"px","top":"18","right":"38","bottom":"18","left":"38","isLinked":""},"border_width":{"unit":"px","top":"4","right":"4","bottom":"4","left":"4","isLinked":"1"},"border_color":"#2572ff","_margin":{"unit":"px","top":"30","right":"0","bottom":"0","left":"0","isLinked":""},"align_tablet":"center","_css_classes":"envato-kit-128-grad-border","selected_icon":{"value":"fas fa-arrow-right","library":"fa-solid"}},"elements":[],"widgetType":"button"}],"isInner":""}],"isInner":""},{"id":"4902c235","elType":"section","settings":{"margin":{"unit":"px","top":"-60","right":"0","bottom":"0","left":"0","isLinked":""},"padding":{"unit":"px","top":"0","right":"0","bottom":"40","left":"0","isLinked":""}},"elements":[{"id":"4026488f","elType":"column","settings":{"_column_size":"100","padding_tablet":{"unit":"em","top":"2","right":"10","bottom":"0","left":"12","isLinked":""}},"elements":[{"id":"2144e7df","elType":"widget","settings":{"image":{"id":"4171","url":"https:\/\/ponceleon.site\/demos\/wp-content\/uploads\/sites\/84\/2021\/03\/connector-flip.png"},"image_size":"full","_animation":"fadeInDown","_margin":{"unit":"px","top":"0","right":"0","bottom":"0","left":"0","isLinked":""},"_z_index":"9"},"elements":[],"widgetType":"image"}],"isInner":""}],"isInner":""},{"id":"ad73994","elType":"section","settings":{"background_background":"gradient","background_color":"#2572ff","padding":{"unit":"px","top":"80","right":"0","bottom":"80","left":"0","isLinked":""},"background_color_b":"#e032a6","background_gradient_angle":{"unit":"deg","size":"90"},"padding_mobile":{"unit":"px","top":"60","right":"20","bottom":"60","left":"20","isLinked":""},"animation":"fadeIn","background_overlay_background":"classic","background_overlay_image":{"id":"4172","url":"https:\/\/ponceleon.site\/demos\/wp-content\/uploads\/sites\/84\/2021\/03\/shape-gradient.png"},"background_overlay_position":"top right","background_overlay_attachment":"fixed","background_overlay_size":"cover","border_width":{"unit":"px","top":"0","right":"60","bottom":"0","left":"60","isLinked":""},"border_color":"#f4f4f4","box_shadow_box_shadow":{"horizontal":"-1","vertical":"35","blur":"52","spread":"-28","color":"rgba(0,0,0,0.5)"},"z_index":"8","shape_divider_top":"curve","shape_divider_top_width":{"unit":"%","size":"180"},"shape_divider_top_negative":"yes"},"elements":[{"id":"17adae9f","elType":"column","settings":{"_column_size":"100"},"elements":[{"id":"5a0048a1","elType":"widget","settings":{"title":"We Produce Emotion","align":"center","align_tablet":"center","title_color":"#ffffff","typography_typography":"custom","typography_font_family":"Fredoka One","typography_font_size":{"unit":"rem","size":"3"},"typography_text_transform":"capitalize","typography_line_height":{"unit":"em","size":"1.4"},"typography_font_weight":"100","_animation":"fadeIn"},"elements":[],"widgetType":"heading"},{"id":"7df9c50e","elType":"widget","settings":{"align":"center","text_color":"#ffffff","typography_typography":"custom","typography_font_family":"Nunito","typography_font_size":{"unit":"rem","size":"1.2"},"typography_line_height":{"unit":"px","size":"24"},"editor":"<p>Provide your mobile users with<br \/>the best experience by sharing the most<br \/>detailed images.<\/p>","_margin":{"unit":"px","top":"0","right":"0","bottom":"50","left":"0","isLinked":""},"typography_font_weight":"bold"},"elements":[],"widgetType":"text-editor"},{"id":"57bab0ca","elType":"section","settings":{"structure":"30","gap":"extended"},"elements":[{"id":"70a68026","elType":"column","settings":{"_column_size":"33","border_border":"solid","border_width":{"unit":"px","top":"2","right":"2","bottom":"2","left":"2","isLinked":"1"},"border_color":"#ffffff","border_radius":{"unit":"px","top":"6","right":"6","bottom":"6","left":"6","isLinked":"1"},"margin":{"unit":"px","top":"0","right":"20","bottom":"0","left":"20","isLinked":""},"padding":{"unit":"px","top":"40","right":"40","bottom":"40","left":"40","isLinked":"1"},"_inline_size_tablet":"33","margin_tablet":{"unit":"px","top":"0","right":"0","bottom":"30","left":"0","isLinked":""}},"elements":[{"id":"1d35af7","elType":"widget","settings":{"title":"Great Documentation","align":"center","title_color":"#ffffff","typography_typography":"custom","typography_font_family":"Nunito","typography_font_size":{"unit":"rem","size":""},"typography_line_height":{"unit":"px","size":"30"},"typography_font_weight":"bold"},"elements":[],"widgetType":"heading"},{"id":"431a2e61","elType":"widget","settings":{"align":"center","text_color":"#ffffff","typography_typography":"custom","typography_font_family":"Nunito","typography_font_size":{"unit":"px","size":"16"},"typography_line_height":{"unit":"px","size":"24"},"editor":"<p>Wheter you’re a new or legacy user, our easy to navigate documention will make your experience enjoyable.<\/p>"},"elements":[],"widgetType":"text-editor"},{"id":"3b7297f","elType":"widget","settings":{"text":"Go to Docs","align":"center","size":"md","icon_align":"right","icon_indent":{"unit":"px","size":"21"},"typography_typography":"custom","typography_font_family":"Nunito","typography_font_size":{"unit":"px","size":"12"},"typography_font_weight":"800","typography_text_transform":"uppercase","typography_letter_spacing":{"unit":"px","size":"0.5"},"button_text_color":"#ffffff","background_color":"rgba(251,228,222,0)","border_border":"solid","border_width":{"unit":"px","top":"0","right":"0","bottom":"2","left":"0","isLinked":""},"border_color":"#ffffff","border_radius":{"unit":"px","top":"0","right":"0","bottom":"0","left":"0","isLinked":"1"},"text_padding":{"unit":"px","top":"14","right":"20","bottom":"8","left":"20","isLinked":""},"typography_line_height":{"unit":"px","size":"12"},"hover_color":"#2572ff","button_background_hover_color":"#ffffff"},"elements":[],"widgetType":"button"}],"isInner":"1"},{"id":"14bec55","elType":"column","settings":{"_column_size":"33","border_border":"solid","border_width":{"unit":"px","top":"2","right":"2","bottom":"2","left":"2","isLinked":"1"},"border_color":"#ffffff","border_radius":{"unit":"px","top":"6","right":"6","bottom":"6","left":"6","isLinked":"1"},"margin":{"unit":"px","top":"0","right":"20","bottom":"0","left":"20","isLinked":""},"padding":{"unit":"px","top":"40","right":"40","bottom":"40","left":"40","isLinked":"1"},"_inline_size_tablet":"33","margin_tablet":{"unit":"px","top":"0","right":"0","bottom":"30","left":"0","isLinked":""}},"elements":[{"id":"1acd7b74","elType":"widget","settings":{"title":"Start Blogging","align":"center","title_color":"#ffffff","typography_typography":"custom","typography_font_family":"Nunito","typography_font_size":{"unit":"rem","size":""},"typography_line_height":{"unit":"px","size":"30"},"typography_font_weight":"bold"},"elements":[],"widgetType":"heading"},{"id":"75069e39","elType":"widget","settings":{"align":"center","text_color":"#ffffff","typography_typography":"custom","typography_font_family":"Nunito","typography_font_size":{"unit":"px","size":"16"},"typography_line_height":{"unit":"px","size":"24"},"editor":"<p>Wheter you’re a new or legacy user, our easy to navigate documention will make your experience enjoyable.<\/p>"},"elements":[],"widgetType":"text-editor"},{"id":"6262fbac","elType":"widget","settings":{"text":"Go to Blog","align":"center","size":"md","icon_align":"right","icon_indent":{"unit":"px","size":"21"},"typography_typography":"custom","typography_font_family":"Nunito","typography_font_size":{"unit":"px","size":"12"},"typography_font_weight":"800","typography_text_transform":"uppercase","typography_letter_spacing":{"unit":"px","size":"0.5"},"button_text_color":"#ffffff","background_color":"rgba(251,228,222,0)","border_border":"solid","border_width":{"unit":"px","top":"0","right":"0","bottom":"2","left":"0","isLinked":""},"border_color":"#ffffff","border_radius":{"unit":"px","top":"0","right":"0","bottom":"0","left":"0","isLinked":"1"},"text_padding":{"unit":"px","top":"14","right":"20","bottom":"8","left":"20","isLinked":""},"typography_line_height":{"unit":"px","size":"12"},"hover_color":"#2572ff","button_background_hover_color":"#ffffff"},"elements":[],"widgetType":"button"}],"isInner":"1"},{"id":"5e0019b6","elType":"column","settings":{"_column_size":"33","border_border":"solid","border_width":{"unit":"px","top":"2","right":"2","bottom":"2","left":"2","isLinked":"1"},"border_color":"#ffffff","border_radius":{"unit":"px","top":"6","right":"6","bottom":"6","left":"6","isLinked":"1"},"margin":{"unit":"px","top":"0","right":"20","bottom":"0","left":"20","isLinked":""},"padding":{"unit":"px","top":"40","right":"40","bottom":"40","left":"40","isLinked":"1"},"_inline_size_tablet":"33","margin_tablet":{"unit":"px","top":"0","right":"0","bottom":"30","left":"0","isLinked":""}},"elements":[{"id":"7747b1e5","elType":"widget","settings":{"title":"Easy Shopping","align":"center","title_color":"#ffffff","typography_typography":"custom","typography_font_family":"Nunito","typography_font_size":{"unit":"rem","size":""},"typography_line_height":{"unit":"px","size":"30"},"typography_font_weight":"bold"},"elements":[],"widgetType":"heading"},{"id":"6ef8a183","elType":"widget","settings":{"align":"center","text_color":"#ffffff","typography_typography":"custom","typography_font_family":"Nunito","typography_font_size":{"unit":"px","size":"16"},"typography_line_height":{"unit":"px","size":"24"},"editor":"<p>Creative layouts to build your great shop, powered by the most popular WordPress eCommerce engine.<\/p>"},"elements":[],"widgetType":"text-editor"},{"id":"12324c54","elType":"widget","settings":{"text":"Go to Demo","align":"center","size":"md","icon_align":"right","icon_indent":{"unit":"px","size":"21"},"typography_typography":"custom","typography_font_family":"Nunito","typography_font_size":{"unit":"px","size":"12"},"typography_font_weight":"800","typography_text_transform":"uppercase","typography_letter_spacing":{"unit":"px","size":"0.5"},"button_text_color":"#ffffff","background_color":"rgba(251,228,222,0)","border_border":"solid","border_width":{"unit":"px","top":"0","right":"0","bottom":"2","left":"0","isLinked":""},"border_color":"#ffffff","border_radius":{"unit":"px","top":"0","right":"0","bottom":"0","left":"0","isLinked":"1"},"text_padding":{"unit":"px","top":"14","right":"20","bottom":"8","left":"20","isLinked":""},"typography_line_height":{"unit":"px","size":"12"},"hover_color":"#2572ff","button_background_hover_color":"#ffffff"},"elements":[],"widgetType":"button"}],"isInner":"1"}],"isInner":"1"},{"id":"dcc450","elType":"widget","settings":{"text":"Buy Now","align":"center","size":"md","icon":"fa fa-arrow-right","icon_align":"right","icon_indent":{"unit":"px","size":"21"},"typography_typography":"custom","typography_font_family":"Poppins","typography_font_size":{"unit":"px","size":"14"},"typography_font_weight":"600","typography_text_transform":"uppercase","typography_letter_spacing":{"unit":"px","size":"0.5"},"button_text_color":"#2572ff","background_color":"#ffffff","hover_color":"#ffffff","button_background_hover_color":"#2572ff","border_radius":{"unit":"px","top":"50","right":"50","bottom":"50","left":"50","isLinked":"1"},"text_padding":{"unit":"px","top":"18","right":"38","bottom":"18","left":"38","isLinked":""},"border_border":"solid","border_width":{"unit":"px","top":"2","right":"2","bottom":"2","left":"2","isLinked":"1"},"border_color":"rgba(255,255,255,0)","_margin":{"unit":"px","top":"60","right":"0","bottom":"0","left":"0","isLinked":""},"_margin_mobile":{"unit":"px","top":"40","right":"0","bottom":"0","left":"0","isLinked":""},"selected_icon":{"value":"fas fa-arrow-right","library":"fa-solid"}},"elements":[],"widgetType":"button"}],"isInner":""}],"isInner":""},{"id":"6733b49","elType":"section","settings":{"structure":"20","padding":{"unit":"px","top":"40","right":"0","bottom":"80","left":"0","isLinked":""},"padding_tablet":{"unit":"px","top":"60","right":"20","bottom":"60","left":"20","isLinked":""},"background_image":{"id":"4173","url":"https:\/\/ponceleon.site\/demos\/wp-content\/uploads\/sites\/84\/2021\/03\/shapeoverlay1.png"},"background_position":"initial","background_repeat":"no-repeat","background_size":"cover","border_border":"solid","border_width":{"unit":"px","top":"1","right":"0","bottom":"0","left":"0","isLinked":""},"border_color":"#eeeeee","margin":{"unit":"px","top":"0","right":"0","bottom":"0","left":"0","isLinked":""},"margin_mobile":{"unit":"px","top":"0","right":"0","bottom":"0","left":"0","isLinked":""},"background_ypos":{"unit":"%","size":"70"}},"elements":[{"id":"342c4c14","elType":"column","settings":{"_column_size":"50","_inline_size":"50","_inline_size_tablet":"100","content_position":"top","margin":{"unit":"px","top":"0","right":"0","bottom":"0","left":"0","isLinked":""},"margin_tablet":{"unit":"px","top":"0","right":"0","bottom":"0","left":"0","isLinked":""},"padding":{"unit":"em","top":"5","right":"3","bottom":"5","left":"5","isLinked":""},"animation":"fadeIn"},"elements":[{"id":"7c12b99d","elType":"widget","settings":{"title":"Awesome Features","align":"left","align_tablet":"center","title_color":"#4054b2","typography_typography":"custom","typography_font_family":"Nunito","typography_font_size":{"unit":"px","size":"18"},"typography_text_transform":"capitalize","typography_line_height":{"unit":"px","size":"30"},"header_size":"h4","_margin":{"unit":"px","top":"0","right":"0","bottom":"-10","left":"0","isLinked":""},"_padding":{"unit":"px","top":"0","right":"0","bottom":"0","left":"0","isLinked":""},"typography_font_weight":"400","typography_font_style":"italic"},"elements":[],"widgetType":"heading"},{"id":"43de3b71","elType":"widget","settings":{"title":"Fully Responsive","align":"left","align_tablet":"center","title_color":"#4054b2","typography_typography":"custom","typography_font_family":"Fredoka One","typography_font_size":{"unit":"rem","size":"2.5"},"typography_text_transform":"capitalize","typography_line_height":{"unit":"em","size":"1.4"},"_animation":"fadeIn","typography_font_weight":"100"},"elements":[],"widgetType":"heading"},{"id":"6558c580","elType":"widget","settings":{"align":"left","typography_typography":"custom","typography_font_family":"Nunito","typography_font_size":{"unit":"px","size":"16"},"typography_line_height":{"unit":"px","size":"24"},"editor":"<p>Provide your mobile users with the best experience by sharing the most detailed images.<\/p><p>Lorem ipsum dolor sit amet, consectetur adipiscing elit. Ut elit tellus, luctus nec ullamcorper mattis, pulvinar dapibus leo.<\/p>","align_tablet":"center"},"elements":[],"widgetType":"text-editor"},{"id":"1a335b4f","elType":"widget","settings":{"text":"Test Now","align":"left","size":"md","icon":"fa fa-arrow-right","icon_align":"right","icon_indent":{"unit":"px","size":"21"},"typography_typography":"custom","typography_font_family":"Nunito","typography_font_size":{"unit":"px","size":"14"},"typography_font_weight":"900","typography_text_transform":"uppercase","typography_letter_spacing":{"unit":"px","size":"0.5"},"button_text_color":"#2572ff","background_color":"#ffffff","hover_color":"#ffffff","button_background_hover_color":"#2572ff","border_radius":{"unit":"px","top":"50","right":"50","bottom":"50","left":"50","isLinked":"1"},"text_padding":{"unit":"px","top":"18","right":"38","bottom":"18","left":"38","isLinked":""},"border_width":{"unit":"px","top":"4","right":"4","bottom":"4","left":"4","isLinked":"1"},"border_color":"#2572ff","_margin":{"unit":"px","top":"30","right":"0","bottom":"0","left":"0","isLinked":""},"align_tablet":"center","_css_classes":"envato-kit-128-grad-border","selected_icon":{"value":"fas fa-arrow-right","library":"fa-solid"}},"elements":[],"widgetType":"button"}],"isInner":""},{"id":"49526d6a","elType":"column","settings":{"_column_size":"50","content_position":"center","background_image":{"id":"4174","url":"https:\/\/ponceleon.site\/demos\/wp-content\/uploads\/sites\/84\/2021\/03\/hugo-barbosa-670010-unsplash.png"},"background_position":"center right","background_repeat":"no-repeat","background_size":"contain","_inline_size_tablet":"100"},"elements":[{"id":"46e6da39","elType":"widget","settings":{"youtube_url":"https:\/\/www.youtube.com\/watch?v=9uOETcuFjbE","vimeo_url":"https:\/\/vimeo.com\/235215203","dailymotion_url":"https:\/\/www.dailymotion.com\/video\/x6koazf","show_image_overlay":"yes","image_overlay":{"id":"4160","url":"https:\/\/ponceleon.site\/demos\/wp-content\/uploads\/sites\/84\/2021\/03\/image-from-rawpixel-id-456067-deriv-1.png"},"lightbox":"yes","play_icon_color":"#2572ff","play_icon_size":{"unit":"px","size":"80"},"play_icon_text_shadow_text_shadow_type":"yes","play_icon_text_shadow_text_shadow":{"horizontal":"0","vertical":"0","blur":"10","color":"rgba(0,0,0,0)"},"_animation":"fadeIn"},"elements":[],"widgetType":"video"}],"isInner":""}],"isInner":""},{"id":"13c00a8f","elType":"section","settings":{"background_background":"classic","background_position":"initial","background_repeat":"repeat-y","background_size":"cover","background_overlay_background":"classic","background_overlay_position":"initial","background_overlay_repeat":"no-repeat","background_overlay_size":"initial","background_overlay_opacity":{"unit":"px","size":"1"},"padding":{"unit":"px","top":"0140","right":"0","bottom":"80","left":"0","isLinked":""},"background_color":"#ffffff","layout":"full_width","background_xpos":{"unit":"%","size":"50"},"background_ypos":{"unit":"px","size":"-17"},"background_bg_width":{"unit":"px","size":"877"},"background_overlay_color":"#ffffff","background_overlay_image":{"id":"4175","url":"https:\/\/ponceleon.site\/demos\/wp-content\/uploads\/sites\/84\/2021\/03\/mountains-graphic-cc0.png"},"background_overlay_xpos":{"unit":"px","size":"175"},"background_overlay_bg_width":{"unit":"vw","size":"100"},"css_filters_saturate":{"unit":"px","size":"0"},"shape_divider_top":"curve","shape_divider_top_width":{"unit":"%","size":"124"},"shape_divider_top_negative":"yes","background_overlay_image_mobile":{"id":"4175","url":"https:\/\/ponceleon.site\/demos\/wp-content\/uploads\/sites\/84\/2021\/03\/mountains-graphic-cc0.png"},"background_overlay_position_mobile":"bottom right","background_overlay_xpos_mobile":{"unit":"px","size":"-41"},"background_overlay_ypos_mobile":{"unit":"px","size":"-244"},"background_overlay_size_mobile":"initial","margin_mobile":{"unit":"px","top":"0","right":"0","bottom":"0","left":"0","isLinked":"1"},"padding_mobile":{"unit":"em","top":"","right":"","bottom":"","left":"","isLinked":"1"}},"elements":[{"id":"6014f494","elType":"column","settings":{"_column_size":"100","padding":{"unit":"px","top":"0","right":"0","bottom":"0","left":"0","isLinked":""}},"elements":[{"id":"3a66b262","elType":"section","settings":{"content_width":{"unit":"px","size":"700"}},"elements":[{"id":"245585d6","elType":"column","settings":{"_column_size":"100","margin_tablet":{"unit":"%","top":"0","right":"36","bottom":"0","left":"0","isLinked":""},"margin_mobile":{"unit":"px","top":"0","right":"0","bottom":"0","left":"0","isLinked":"1"}},"elements":[{"id":"6679aff8","elType":"widget","settings":{"image":{"id":"4176","url":"https:\/\/ponceleon.site\/demos\/wp-content\/uploads\/sites\/84\/2021\/03\/connector.png"},"image_size":"full","_animation":"fadeInDown","_margin":{"unit":"px","top":"-230","right":"0","bottom":"80","left":"0","isLinked":""}},"elements":[],"widgetType":"image"},{"id":"29d050c0","elType":"widget","settings":{"title":"Your Content. Your Way","align":"center","align_tablet":"left","title_color":"#000000","typography_typography":"custom","typography_font_family":"Fredoka One","typography_font_size":{"unit":"rem","size":"3"},"typography_text_transform":"capitalize","typography_line_height":{"unit":"em","size":"1.4"},"_animation":"fadeIn","typography_font_weight":"100","align_mobile":"center","typography_font_size_tablet":{"unit":"px","size":"37"},"_margin_mobile":{"unit":"px","top":"0","right":"0","bottom":"0","left":"0","isLinked":"1"},"_padding_mobile":{"unit":"px","top":"0","right":"0","bottom":"0","left":"0","isLinked":"1"}},"elements":[],"widgetType":"heading"},{"id":"66e66414","elType":"widget","settings":{"align":"center","typography_typography":"custom","typography_font_family":"Nunito","typography_font_size":{"unit":"px","size":"16"},"typography_line_height":{"unit":"px","size":"24"},"editor":"<p>Te maiorum pericula neglegentur sit, pro fabulas iracundia ad. Ne vim facilis feugait moderatius, nec eu perpetua scriptorem referrentur. Ut alii delicata mei. <\/p>","align_tablet":"left","_margin_tablet":{"unit":"px","top":"-20","right":"0","bottom":"0","left":"0","isLinked":""},"_padding_tablet":{"unit":"px","top":"0","right":"0","bottom":"0","left":"0","isLinked":""},"align_mobile":"center"},"elements":[],"widgetType":"text-editor"}],"isInner":"1"}],"isInner":"1"},{"id":"60709dd9","elType":"section","settings":{"structure":"80","margin":{"unit":"px","top":"50","right":"0","bottom":"40","left":"0","isLinked":""},"margin_tablet":{"unit":"px","top":"30","right":"0","bottom":"0","left":"0","isLinked":""},"animation":"fadeIn","layout":"full_width"},"elements":[{"id":"61c2ab76","elType":"column","settings":{"_column_size":"12","_inline_size_tablet":"50","margin_tablet":{"unit":"px","top":"40","right":"0","bottom":"0","left":"0","isLinked":""}},"elements":[{"id":"6bb91476","elType":"widget","settings":{"image":{"id":"4177","url":"https:\/\/ponceleon.site\/demos\/wp-content\/uploads\/sites\/84\/2021\/03\/masonry.png"},"image_border_radius":{"unit":"px","top":"4","right":"4","bottom":"4","left":"4","isLinked":"1"},"image_box_shadow_box_shadow_type":"yes","image_box_shadow_box_shadow":{"horizontal":"-10","vertical":"-10","blur":"50","spread":"0","color":"rgba(0,0,0,0.1)"},"align":"center","width":{"unit":"%","size":"51"}},"elements":[],"widgetType":"image"}],"isInner":"1"},{"id":"3fca3b0e","elType":"column","settings":{"_column_size":"12","_inline_size_tablet":"50","margin_tablet":{"unit":"px","top":"40","right":"0","bottom":"0","left":"0","isLinked":""}},"elements":[{"id":"60f10722","elType":"widget","settings":{"image":{"id":"4178","url":"https:\/\/ponceleon.site\/demos\/wp-content\/uploads\/sites\/84\/2021\/03\/list.png"},"image_border_radius":{"unit":"px","top":"4","right":"4","bottom":"4","left":"4","isLinked":"1"},"image_box_shadow_box_shadow_type":"yes","image_box_shadow_box_shadow":{"horizontal":"-10","vertical":"-10","blur":"50","spread":"0","color":"rgba(0,0,0,0.1)"},"width":{"unit":"%","size":"81"}},"elements":[],"widgetType":"image"}],"isInner":"1"},{"id":"731976","elType":"column","settings":{"_column_size":"12","_inline_size_tablet":"50"},"elements":[{"id":"31cd9c2b","elType":"widget","settings":{"image":{"id":"4166","url":"https:\/\/ponceleon.site\/demos\/wp-content\/uploads\/sites\/84\/2021\/03\/on_image_like.png"},"image_border_radius":{"unit":"px","top":"4","right":"4","bottom":"4","left":"4","isLinked":"1"},"image_box_shadow_box_shadow_type":"yes","image_box_shadow_box_shadow":{"horizontal":"-10","vertical":"-10","blur":"50","spread":"0","color":"rgba(0,0,0,0.1)"}},"elements":[],"widgetType":"image"}],"isInner":"1"},{"id":"ab420b7","elType":"column","settings":{"_column_size":"12","_inline_size_tablet":"50","margin_tablet":{"unit":"px","top":"40","right":"0","bottom":"0","left":"0","isLinked":""}},"elements":[{"id":"324e8d79","elType":"widget","settings":{"image":{"id":"4169","url":"https:\/\/ponceleon.site\/demos\/wp-content\/uploads\/sites\/84\/2021\/03\/default.png"},"image_border_radius":{"unit":"px","top":"4","right":"4","bottom":"4","left":"4","isLinked":"1"},"image_box_shadow_box_shadow_type":"yes","image_box_shadow_box_shadow":{"horizontal":"-10","vertical":"-10","blur":"50","spread":"0","color":"rgba(0,0,0,0.1)"},"align":"center","width":{"unit":"%","size":"61"},"_margin_mobile":{"unit":"px","top":"0","right":"0","bottom":"0","left":"0","isLinked":"1"},"_padding_mobile":{"unit":"px","top":"0","right":"0","bottom":"0","left":"0","isLinked":"1"}},"elements":[],"widgetType":"image"}],"isInner":"1"},{"id":"44178d86","elType":"column","settings":{"_column_size":"12","_inline_size_tablet":"50","content_position":"center"},"elements":[{"id":"37699f28","elType":"widget","settings":{"image":{"id":"4167","url":"https:\/\/ponceleon.site\/demos\/wp-content\/uploads\/sites\/84\/2021\/03\/under_image.png"},"image_border_radius":{"unit":"px","top":"4","right":"4","bottom":"4","left":"4","isLinked":"1"},"image_box_shadow_box_shadow_type":"yes","image_box_shadow_box_shadow":{"horizontal":"-10","vertical":"-10","blur":"50","spread":"0","color":"rgba(0,0,0,0.1)"},"align":"center","width":{"unit":"%","size":"53"},"_margin_mobile":{"unit":"px","top":"0","right":"0","bottom":"0","left":"0","isLinked":"1"},"_padding_mobile":{"unit":"px","top":"0","right":"0","bottom":"0","left":"0","isLinked":"1"}},"elements":[],"widgetType":"image"}],"isInner":"1"},{"id":"6b179b2f","elType":"column","settings":{"_column_size":"12","_inline_size_tablet":"50","margin_tablet":{"unit":"px","top":"40","right":"0","bottom":"0","left":"0","isLinked":""}},"elements":[{"id":"7167c793","elType":"widget","settings":{"image":{"id":"4168","url":"https:\/\/ponceleon.site\/demos\/wp-content\/uploads\/sites\/84\/2021\/03\/on_image.png"},"image_border_radius":{"unit":"px","top":"4","right":"4","bottom":"4","left":"4","isLinked":"1"},"image_box_shadow_box_shadow_type":"yes","image_box_shadow_box_shadow":{"horizontal":"-10","vertical":"-10","blur":"50","spread":"0","color":"rgba(0,0,0,0.1)"},"align":"left","width":{"unit":"%","size":"82"},"align_mobile":"center","_margin_mobile":{"unit":"px","top":"0","right":"0","bottom":"0","left":"0","isLinked":"1"},"_padding_mobile":{"unit":"px","top":"0","right":"0","bottom":"0","left":"0","isLinked":"1"}},"elements":[],"widgetType":"image"}],"isInner":"1"},{"id":"5f8a979","elType":"column","settings":{"_column_size":"12","_inline_size_tablet":"50","margin_tablet":{"unit":"px","top":"40","right":"0","bottom":"0","left":"0","isLinked":""},"content_position":"center"},"elements":[{"id":"39cfccbd","elType":"widget","settings":{"image":{"id":"4170","url":"https:\/\/ponceleon.site\/demos\/wp-content\/uploads\/sites\/84\/2021\/03\/masonry_border.png"},"image_border_radius":{"unit":"px","top":"4","right":"4","bottom":"4","left":"4","isLinked":"1"},"image_box_shadow_box_shadow_type":"yes","image_box_shadow_box_shadow":{"horizontal":"-10","vertical":"-10","blur":"50","spread":"0","color":"rgba(0,0,0,0.1)"},"align":"center","_margin":{"unit":"px","top":"0","right":"0","bottom":"0","left":"0","isLinked":""}},"elements":[],"widgetType":"image"}],"isInner":"1"},{"id":"17220c1e","elType":"column","settings":{"_column_size":"12","_inline_size_tablet":"50","margin_tablet":{"unit":"px","top":"40","right":"0","bottom":"0","left":"0","isLinked":""}},"elements":[{"id":"7701d7aa","elType":"widget","settings":{"image":{"id":"4179","url":"https:\/\/ponceleon.site\/demos\/wp-content\/uploads\/sites\/84\/2021\/03\/under_image_border.png"},"image_border_radius":{"unit":"px","top":"4","right":"4","bottom":"4","left":"4","isLinked":"1"},"image_box_shadow_box_shadow_type":"yes","image_box_shadow_box_shadow":{"horizontal":"-10","vertical":"-10","blur":"50","spread":"0","color":"rgba(0,0,0,0.1)"},"width":{"unit":"%","size":"58"},"_margin_mobile":{"unit":"px","top":"0","right":"0","bottom":"0","left":"0","isLinked":"1"},"_padding_mobile":{"unit":"px","top":"0","right":"0","bottom":"0","left":"0","isLinked":"1"}},"elements":[],"widgetType":"image"}],"isInner":"1"}],"isInner":"1"},{"id":"4371fa80","elType":"section","settings":{"structure":"20"},"elements":[{"id":"1a0c139c","elType":"column","settings":{"_column_size":"50"},"elements":[{"id":"16eca564","elType":"widget","settings":{"text":"Free Download","align":"right","size":"md","icon_align":"right","icon_indent":{"unit":"px","size":"14"},"typography_typography":"custom","typography_font_family":"Nunito","typography_font_size":{"unit":"px","size":"14"},"typography_font_weight":"900","typography_text_transform":"uppercase","typography_letter_spacing":{"unit":"px","size":"0.5"},"button_text_color":"#ffffff","background_color":"#2572ff","hover_color":"#ffffff","button_background_hover_color":"#ff26cc","border_radius":{"unit":"px","top":"30","right":"30","bottom":"30","left":"30","isLinked":"1"},"text_padding":{"unit":"px","top":"20","right":"40","bottom":"20","left":"40","isLinked":""},"border_width":{"unit":"px","top":"2","right":"2","bottom":"2","left":"2","isLinked":"1"},"border_color":"#2572ff","align_tablet":"right","_margin":{"unit":"px","top":"30","right":"0","bottom":"0","left":"0","isLinked":""},"_margin_mobile":{"unit":"px","top":"0","right":"0","bottom":"0","left":"0","isLinked":""},"_padding":{"unit":"px","top":"0","right":"0","bottom":"0","left":"0","isLinked":"1"},"_animation":"fadeIn","icon":"fa fa-cloud-download","align_mobile":"center","selected_icon":{"value":"fas fa-cloud-download-alt","library":"fa-solid"}},"elements":[],"widgetType":"button"}],"isInner":"1"},{"id":"a0453f8","elType":"column","settings":{"_column_size":"50","margin_mobile":{"unit":"px","top":"0","right":"0","bottom":"0","left":"0","isLinked":"1"},"padding_mobile":{"unit":"px","top":"0","right":"0","bottom":"0","left":"0","isLinked":"1"}},"elements":[{"id":"35bbbcb1","elType":"widget","settings":{"text":"All Features","align":"left","size":"md","icon":"fa fa-arrow-right","icon_align":"right","icon_indent":{"unit":"px","size":"21"},"typography_typography":"custom","typography_font_family":"Nunito","typography_font_size":{"unit":"px","size":"14"},"typography_font_weight":"900","typography_text_transform":"uppercase","typography_letter_spacing":{"unit":"px","size":"0.5"},"button_text_color":"#2572ff","background_color":"#ffffff","hover_color":"#ffffff","button_background_hover_color":"#2572ff","border_radius":{"unit":"px","top":"50","right":"50","bottom":"50","left":"50","isLinked":"1"},"text_padding":{"unit":"px","top":"18","right":"38","bottom":"18","left":"38","isLinked":""},"border_width":{"unit":"px","top":"4","right":"4","bottom":"4","left":"4","isLinked":"1"},"border_color":"#2572ff","_margin":{"unit":"px","top":"30","right":"0","bottom":"0","left":"0","isLinked":""},"align_tablet":"left","_css_classes":"envato-kit-128-grad-border","align_mobile":"center","selected_icon":{"value":"fas fa-arrow-right","library":"fa-solid"}},"elements":[],"widgetType":"button"}],"isInner":"1"}],"isInner":"1"}],"isInner":""}],"isInner":""}]},{"meta_id":"22666","post_id":"4154","meta_key":"_elementor_page_settings","meta_value":"a:1:{s:10:\"hide_title\";s:3:\"yes\";}"},{"meta_id":"22665","post_id":"4154","meta_key":"_wp_page_template","meta_value":"elementor_canvas"},{"meta_id":"22675","post_id":"4154","meta_key":"_elementor_controls_usage","meta_value":"a:9:{s:7:\"heading\";a:3:{s:5:\"count\";i:10;s:15:\"control_percent\";i:6;s:8:\"controls\";a:3:{s:7:\"content\";a:1:{s:13:\"section_title\";a:5:{s:5:\"title\";i:10;s:11:\"header_size\";i:3;s:5:\"align\";i:10;s:12:\"align_tablet\";i:7;s:12:\"align_mobile\";i:1;}}s:5:\"style\";a:1:{s:19:\"section_title_style\";a:12:{s:11:\"title_color\";i:10;s:21:\"typography_typography\";i:10;s:22:\"typography_font_family\";i:10;s:20:\"typography_font_size\";i:10;s:25:\"typography_text_transform\";i:7;s:22:\"typography_line_height\";i:10;s:27:\"typography_font_size_mobile\";i:1;s:29:\"typography_line_height_mobile\";i:1;s:22:\"typography_font_weight\";i:10;s:25:\"typography_letter_spacing\";i:1;s:21:\"typography_font_style\";i:2;s:27:\"typography_font_size_tablet\";i:1;}}s:8:\"advanced\";a:2:{s:14:\"_section_style\";a:4:{s:7:\"_margin\";i:3;s:8:\"_padding\";i:2;s:14:\"_margin_mobile\";i:1;s:15:\"_padding_mobile\";i:1;}s:15:\"section_effects\";a:1:{s:10:\"_animation\";i:5;}}}}s:6:\"spacer\";a:3:{s:5:\"count\";i:4;s:15:\"control_percent\";i:4;s:8:\"controls\";a:2:{s:7:\"content\";a:1:{s:14:\"section_spacer\";a:2:{s:5:\"space\";i:4;s:12:\"space_tablet\";i:3;}}s:8:\"advanced\";a:3:{s:19:\"_section_background\";a:4:{s:22:\"_background_background\";i:3;s:17:\"_background_image\";i:3;s:20:\"_background_position\";i:2;s:16:\"_background_size\";i:2;}s:15:\"_section_border\";a:3:{s:14:\"_border_radius\";i:3;s:27:\"_box_shadow_box_shadow_type\";i:3;s:22:\"_box_shadow_box_shadow\";i:3;}s:14:\"_section_style\";a:2:{s:7:\"_margin\";i:3;s:14:\"_margin_tablet\";i:3;}}}}s:11:\"text-editor\";a:3:{s:5:\"count\";i:8;s:15:\"control_percent\";i:4;s:8:\"controls\";a:3:{s:5:\"style\";a:1:{s:13:\"section_style\";a:10:{s:5:\"align\";i:8;s:10:\"text_color\";i:5;s:21:\"typography_typography\";i:8;s:22:\"typography_font_family\";i:8;s:20:\"typography_font_size\";i:8;s:22:\"typography_line_height\";i:8;s:12:\"align_tablet\";i:4;s:21:\"typography_font_style\";i:1;s:22:\"typography_font_weight\";i:1;s:12:\"align_mobile\";i:1;}}s:7:\"content\";a:1:{s:14:\"section_editor\";a:1:{s:6:\"editor\";i:8;}}s:8:\"advanced\";a:1:{s:14:\"_section_style\";a:4:{s:7:\"_margin\";i:2;s:8:\"_padding\";i:1;s:14:\"_margin_tablet\";i:1;s:15:\"_padding_tablet\";i:1;}}}}s:6:\"button\";a:3:{s:5:\"count\";i:9;s:15:\"control_percent\";i:9;s:8:\"controls\";a:3:{s:7:\"content\";a:1:{s:14:\"section_button\";a:8:{s:4:\"text\";i:9;s:5:\"align\";i:9;s:4:\"size\";i:9;s:10:\"icon_align\";i:9;s:11:\"icon_indent\";i:9;s:12:\"align_tablet\";i:5;s:13:\"selected_icon\";i:5;s:12:\"align_mobile\";i:2;}}s:5:\"style\";a:1:{s:13:\"section_style\";a:16:{s:21:\"typography_typography\";i:9;s:22:\"typography_font_family\";i:9;s:20:\"typography_font_size\";i:9;s:22:\"typography_font_weight\";i:9;s:25:\"typography_text_transform\";i:9;s:25:\"typography_letter_spacing\";i:9;s:17:\"button_text_color\";i:9;s:16:\"background_color\";i:9;s:11:\"hover_color\";i:9;s:29:\"button_background_hover_color\";i:9;s:13:\"border_radius\";i:9;s:12:\"text_padding\";i:9;s:12:\"border_width\";i:9;s:12:\"border_color\";i:8;s:13:\"border_border\";i:4;s:22:\"typography_line_height\";i:3;}}s:8:\"advanced\";a:2:{s:14:\"_section_style\";a:4:{s:7:\"_margin\";i:6;s:14:\"_margin_mobile\";i:3;s:8:\"_padding\";i:2;s:12:\"_css_classes\";i:3;}s:15:\"section_effects\";a:1:{s:10:\"_animation\";i:2;}}}}s:6:\"column\";a:3:{s:5:\"count\";i:33;s:15:\"control_percent\";i:0;s:8:\"controls\";a:3:{s:6:\"layout\";a:1:{s:6:\"layout\";a:3:{s:19:\"_inline_size_tablet\";i:27;s:16:\"content_position\";i:11;s:12:\"_inline_size\";i:5;}}s:8:\"advanced\";a:2:{s:16:\"section_advanced\";a:6:{s:6:\"margin\";i:11;s:7:\"padding\";i:12;s:13:\"margin_tablet\";i:21;s:13:\"margin_mobile\";i:4;s:14:\"padding_mobile\";i:3;s:14:\"padding_tablet\";i:4;}s:15:\"section_effects\";a:1:{s:9:\"animation\";i:5;}}s:5:\"style\";a:3:{s:13:\"section_style\";a:6:{s:21:\"background_background\";i:2;s:16:\"background_image\";i:2;s:15:\"background_size\";i:3;s:19:\"background_bg_width\";i:1;s:19:\"background_position\";i:2;s:17:\"background_repeat\";i:2;}s:26:\"section_background_overlay\";a:8:{s:29:\"background_overlay_background\";i:1;s:24:\"background_overlay_image\";i:1;s:27:\"background_overlay_position\";i:1;s:25:\"background_overlay_repeat\";i:1;s:23:\"background_overlay_size\";i:1;s:26:\"background_overlay_opacity\";i:1;s:22:\"css_filters_css_filter\";i:1;s:20:\"css_filters_saturate\";i:1;}s:14:\"section_border\";a:4:{s:13:\"border_border\";i:3;s:12:\"border_width\";i:3;s:12:\"border_color\";i:3;s:13:\"border_radius\";i:3;}}}}s:14:\"image-carousel\";a:3:{s:5:\"count\";i:1;s:15:\"control_percent\";i:5;s:8:\"controls\";a:3:{s:7:\"content\";a:2:{s:22:\"section_image_carousel\";a:5:{s:8:\"carousel\";i:1;s:14:\"thumbnail_size\";i:1;s:14:\"slides_to_show\";i:1;s:16:\"slides_to_scroll\";i:1;s:10:\"navigation\";i:1;}s:26:\"section_additional_options\";a:3:{s:14:\"pause_on_hover\";i:1;s:6:\"effect\";i:1;s:14:\"autoplay_speed\";i:1;}}s:5:\"style\";a:2:{s:24:\"section_style_navigation\";a:2:{s:9:\"dots_size\";i:1;s:10:\"dots_color\";i:1;}s:19:\"section_style_image\";a:1:{s:19:\"image_border_radius\";i:1;}}s:8:\"advanced\";a:3:{s:14:\"_section_style\";a:1:{s:14:\"_margin_mobile\";i:1;}s:15:\"section_effects\";a:1:{s:10:\"_animation\";i:1;}s:15:\"_section_border\";a:1:{s:22:\"_box_shadow_box_shadow\";i:1;}}}}s:7:\"section\";a:3:{s:5:\"count\";i:14;s:15:\"control_percent\";i:7;s:8:\"controls\";a:3:{s:6:\"layout\";a:2:{s:17:\"section_structure\";a:1:{s:9:\"structure\";i:9;}s:14:\"section_layout\";a:3:{s:6:\"layout\";i:3;s:3:\"gap\";i:1;s:13:\"content_width\";i:1;}}s:8:\"advanced\";a:2:{s:16:\"section_advanced\";a:7:{s:7:\"z_index\";i:4;s:7:\"padding\";i:7;s:13:\"margin_mobile\";i:4;s:14:\"padding_mobile\";i:5;s:13:\"margin_tablet\";i:5;s:14:\"padding_tablet\";i:5;s:6:\"margin\";i:7;}s:15:\"section_effects\";a:1:{s:9:\"animation\";i:4;}}s:5:\"style\";a:4:{s:18:\"section_background\";a:11:{s:21:\"background_background\";i:5;s:16:\"background_color\";i:5;s:16:\"background_image\";i:2;s:19:\"background_position\";i:4;s:17:\"background_repeat\";i:3;s:15:\"background_size\";i:4;s:15:\"background_xpos\";i:2;s:15:\"background_ypos\";i:3;s:19:\"background_bg_width\";i:2;s:18:\"background_color_b\";i:2;s:25:\"background_gradient_angle\";i:2;}s:21:\"section_shape_divider\";a:8:{s:26:\"shape_divider_bottom_width\";i:1;s:27:\"shape_divider_bottom_height\";i:1;s:29:\"shape_divider_bottom_negative\";i:1;s:17:\"shape_divider_top\";i:3;s:23:\"shape_divider_top_color\";i:2;s:23:\"shape_divider_top_width\";i:4;s:24:\"shape_divider_top_height\";i:2;s:26:\"shape_divider_top_negative\";i:2;}s:14:\"section_border\";a:4:{s:13:\"border_border\";i:2;s:12:\"border_width\";i:3;s:12:\"border_color\";i:3;s:21:\"box_shadow_box_shadow\";i:1;}s:26:\"section_background_overlay\";a:16:{s:24:\"background_overlay_image\";i:3;s:27:\"background_overlay_position\";i:3;s:25:\"background_overlay_repeat\";i:2;s:23:\"background_overlay_size\";i:3;s:26:\"background_overlay_opacity\";i:2;s:29:\"background_overlay_background\";i:2;s:29:\"background_overlay_attachment\";i:1;s:24:\"background_overlay_color\";i:1;s:23:\"background_overlay_xpos\";i:1;s:27:\"background_overlay_bg_width\";i:1;s:20:\"css_filters_saturate\";i:1;s:31:\"background_overlay_image_mobile\";i:1;s:34:\"background_overlay_position_mobile\";i:1;s:30:\"background_overlay_xpos_mobile\";i:1;s:30:\"background_overlay_ypos_mobile\";i:1;s:30:\"background_overlay_size_mobile\";i:1;}}}}s:5:\"image\";a:3:{s:5:\"count\";i:15;s:15:\"control_percent\";i:2;s:8:\"controls\";a:3:{s:7:\"content\";a:1:{s:13:\"section_image\";a:4:{s:5:\"image\";i:15;s:5:\"align\";i:9;s:10:\"image_size\";i:2;s:12:\"align_mobile\";i:1;}}s:5:\"style\";a:1:{s:19:\"section_style_image\";a:4:{s:19:\"image_border_radius\";i:13;s:32:\"image_box_shadow_box_shadow_type\";i:13;s:27:\"image_box_shadow_box_shadow\";i:13;s:5:\"width\";i:11;}}s:8:\"advanced\";a:2:{s:14:\"_section_style\";a:4:{s:7:\"_margin\";i:5;s:8:\"_z_index\";i:1;s:14:\"_margin_mobile\";i:4;s:15:\"_padding_mobile\";i:4;}s:15:\"section_effects\";a:1:{s:10:\"_animation\";i:2;}}}}s:5:\"video\";a:3:{s:5:\"count\";i:1;s:15:\"control_percent\";i:3;s:8:\"controls\";a:3:{s:7:\"content\";a:2:{s:13:\"section_video\";a:2:{s:11:\"youtube_url\";i:1;s:15:\"dailymotion_url\";i:1;}s:21:\"section_image_overlay\";a:3:{s:18:\"show_image_overlay\";i:1;s:13:\"image_overlay\";i:1;s:8:\"lightbox\";i:1;}}s:5:\"style\";a:1:{s:19:\"section_video_style\";a:4:{s:15:\"play_icon_color\";i:1;s:14:\"play_icon_size\";i:1;s:38:\"play_icon_text_shadow_text_shadow_type\";i:1;s:33:\"play_icon_text_shadow_text_shadow\";i:1;}}s:8:\"advanced\";a:1:{s:15:\"section_effects\";a:1:{s:10:\"_animation\";i:1;}}}}}"},{"meta_id":"24509","post_id":"4154","meta_key":"_oembed_d69273210693e69e20053d7cdd3698a0","meta_value":"<iframe title=\"Elementor video placeholder\" width=\"800\" height=\"450\" src=\"https:\/\/www.youtube.com\/embed\/9uOETcuFjbE?feature=oembed\" frameborder=\"0\" allow=\"accelerometer; autoplay; clipboard-write; encrypted-media; gyroscope; picture-in-picture\" allowfullscreen><\/iframe>"},{"meta_id":"24510","post_id":"4154","meta_key":"_oembed_time_d69273210693e69e20053d7cdd3698a0","meta_value":"1614965628"},{"meta_id":"34448","post_id":"4154","meta_key":"_thumbnail_id","meta_value":"6399"},{"meta_id":"41616","post_id":"4154","meta_key":"_elementor_css","meta_value":"a:6:{s:4:\"time\";i:1615985010;s:5:\"fonts\";a:3:{i:0;s:11:\"Fredoka One\";i:1;s:6:\"Nunito\";i:2;s:7:\"Poppins\";}s:5:\"icons\";a:2:{i:0;s:0:\"\";i:1;s:8:\"fa-solid\";}s:20:\"dynamic_elements_ids\";a:0:{}s:6:\"status\";s:4:\"file\";i:0;s:0:\"\";}"},{"meta_id":"41629","post_id":"4154","meta_key":"imagen_larga","meta_value":"6399"},{"meta_id":"41630","post_id":"4154","meta_key":"_imagen_larga","meta_value":"field_6043b5afc4b0a"},{"meta_id":"41631","post_id":"4154","meta_key":"imagen_corta","meta_value":"7065"},{"meta_id":"41632","post_id":"4154","meta_key":"_imagen_corta","meta_value":"field_6050ddfaadfc1"}]